Verision1/02_rlt/LOPD_4bit.sv
module LOPD_4bit(
    input logic [3:0]       i_data  ,
    output logic [1:0]      o_pos_one,
    output logic            o_zero_flag
);

/////////////////// LDO ///////////////////
// D[3] | D[2] | D[1] | D[0] |PO[3] | PO[2] | PO[1] | PO[0] | ZERO_FLAG |
//   0  |   0  |   0  |   0  |  0   |   0   |   0   |   0   |     1     |
//   0  |   0  |   0  |   1  |  0   |   0   |   0   |   1   |     0     |
//   0  |   0  |   1  |   X  |  0   |   0   |   1   |   0   |     0     |
//   0  |   1  |   X  |   X  |  0   |   1   |   0   |   0   |     0     |
//   1  |   X  |   X  |   X  |  1   |   0   |   0   |   0   |     0     |
/////////////////// LDOD ///////////////////
// D[3] | D[2] | D[1] | D[0] | PO[1] | PO[0] | ZERO_FLAG |
//   0  |   0  |   0  |   0  |   0   |   0   |     1     |
//   0  |   0  |   0  |   1  |   0   |   0   |     0     |
//   0  |   0  |   1  |   X  |   0   |   1   |     0     |
//   0  |   1  |   X  |   X  |   1   |   0   |     0     |
//   1  |   X  |   X  |   X  |   1   |   1   |     0     |

// assign o_zero_flag = ~( (i_data[3] | i_data[2]) | (i_data[1] | i_data[0]) ) ;
assign o_zero_flag = ~( |i_data );  // Toán tử reduction OR
assign o_pos_one[1] = i_data[3] | i_data[2];
assign o_pos_one[0] = ((~(i_data[3] | i_data[2])) & (i_data[1])) |  (i_data[3]);

endmodule

Verision1/03_verif/SubModule/LOPD_UNIT/LOPD_4BIT/tb_LOPD_4bit.sv
`timescale 1ns/1ps

module tb_LOPD_4bit();

    // ================= PARAMETERS ================= //
    parameter SIZE_DATA = 4;
    parameter SIZE_POS  = 2; // log2(4) = 2

    // ================= SIGNALS ================= //
    logic [SIZE_DATA-1:0] i_data;
    logic [SIZE_POS-1:0]  o_pos_one;
    logic                 o_zero_flag;

    logic [SIZE_POS-1:0]  w_expect_pos;
    logic                 w_expect_zero;

    int test_count = 0;
    int test_pass  = 0;

    // ================= DUT ================= //
    LOPD_4bit DUT (
        .i_data(i_data),
        .o_pos_one(o_pos_one),
        .o_zero_flag(o_zero_flag)
    );

    // ================= DUMP WAVE ================= //
    initial begin
        $dumpfile("tb_LOPD_4bit.vcd");
        $dumpvars(0, tb_LOPD_4bit);
    end

    // ================= FUNCTION: Reference Model ================= //
    function automatic void f_find_LOPD(
        input  logic [SIZE_DATA-1:0] f_i_data,
        output logic [SIZE_POS-1:0]  f_o_pos_one,
        output logic                 f_o_zero_flag
    );
        int pos;
        begin
            if (f_i_data == 0) begin
                f_o_pos_one   = 0;
                f_o_zero_flag = 1;
            end else begin
                // find position of leading '1'
                for (pos = SIZE_DATA-1; pos >= 0; pos--) begin
                    if (f_i_data[pos]) begin
                        f_o_pos_one   = SIZE_DATA-1 - pos; // distance from MSB
                        f_o_zero_flag = 0;
                        break;
                    end
                end
            end
        end
    endfunction

    // ================= TASK: Display & Compare ================= //
    task automatic Check_Result(
        input string t_name,
        input logic [SIZE_DATA-1:0] t_data,
        input logic [SIZE_POS-1:0] exp_pos,
        input logic                 exp_zero,
        input logic [SIZE_POS-1:0] dut_pos,
        input logic                 dut_zero
    );
        string result;
        result = ((exp_pos == dut_pos) && (exp_zero == dut_zero)) ? "PASS" : "FAIL";
        $display("[%s] data=%b => expect(pos=%0d, zero=%b), dut(pos=%0d, zero=%b) => %s",
                 t_name, t_data, exp_pos, exp_zero, dut_pos, dut_zero, result);
        test_count++;
        if (result == "PASS") test_pass++;
    endtask

    // ================= TEST SEQUENCE ================= //
    initial begin
        $display("\n=== START 4-bit LEADING ONE POSITION DETECTOR TEST ===\n");

        // --- Deterministic test patterns ---
        for (int i = 0; i < 16; i++) begin
            i_data = i[SIZE_DATA-1:0];
            #1;
            f_find_LOPD(i_data, w_expect_pos, w_expect_zero);
            Check_Result("Fixed", i_data, w_expect_pos, w_expect_zero, o_pos_one, o_zero_flag);
        end

        // --- Random test cases ---
        repeat (10) begin
            i_data = $urandom_range(0, (1 << SIZE_DATA) - 1);
            #1;
            f_find_LOPD(i_data, w_expect_pos, w_expect_zero);
            Check_Result("Random", i_data, w_expect_pos, w_expect_zero, o_pos_one, o_zero_flag);
        end

        // --- Summary ---
        #5;
        $display("\n==================================");
        $display("========== TEST SUMMARY ==========");
        $display("Total test cases: %6d", test_count);
        $display("Passed          : %6d", test_pass);
        $display("Failed          : %6d", test_count - test_pass);
        $display("Pass rate       : %0.2f%%", (test_pass * 100.0) / test_count);
        $display("==================================\n");

        #10;
        $finish;
    end

endmodule

Verision1/03_verif/Questasim/tb_LOPD_4bit.vcd
$date
	Mon Nov  3 20:30:44 2025
$end
$version
	Questa Intel Starter FPGA Edition Version 2024.3
$end
$timescale
	1ps
$end

$scope module tb_LOPD_4bit $end
$var parameter 32 ! SIZE_DATA $end
$var parameter 32 " SIZE_POS $end
$var reg 4 # i_data [3:0] $end
$var reg 2 $ o_pos_one [1:0] $end
$var reg 1 % o_zero_flag $end
$var reg 2 & w_expect_pos [1:0] $end
$var reg 1 ' w_expect_zero $end
$var integer 32 ( test_count $end
$var integer 32 ) test_pass $end

$scope function f_find_LOPD $end
$upscope $end

$scope task Check_Result $end
$upscope $end

$scope module DUT $end
$var wire 1 * i_data [3] $end
$var wire 1 + i_data [2] $end
$var wire 1 , i_data [1] $end
$var wire 1 - i_data [0] $end
$var reg 2 . o_pos_one [1:0] $end
$var reg 1 / o_zero_flag $end
$upscope $end
$upscope $end
$enddefinitions $end
#0
$dumpvars
b0 #
b0 $
1%
bx &
x'
b0 .
1/
b100 !
b10 "
b0 (
b0 )
0-
0,
0+
0*
$end
#1000
b0 &
1'
b1 (
b1 )
b1 #
1-
0/
b10 .
b11 .
b11 $
0%
#2000
b11 &
0'
b10 (
b10 )
b10 #
0-
1,
b10 .
b10 $
#3000
b10 &
b11 (
b11 )
b11 #
1-
#4000
b100 (
b100 )
b100 #
0-
0,
1+
b11 .
b1 .
b1 $
#5000
b1 &
b101 (
b101 )
b101 #
1-
#6000
b110 (
b110 )
b110 #
0-
1,
#7000
b111 (
b111 )
b111 #
1-
#8000
b1000 (
b1000 )
b1000 #
0-
0,
0+
1*
b0 .
b0 $
#9000
b0 &
b1001 (
b1001 )
b1001 #
1-
#10000
b1010 (
b1010 )
b1010 #
0-
1,
#11000
b1011 (
b1011 )
b1011 #
1-
#12000
b1100 (
b1100 )
b1100 #
0-
0,
1+
#13000
b1101 (
b1101 )
b1101 #
1-
#14000
b1110 (
b1110 )
b1110 #
0-
1,
#15000
b1111 (
b1111 )
b1111 #
1-
#16000
b10000 (
b10000 )
b1001 #
0,
0+
#17000
b10001 (
b10001 )
b1010 #
0-
1,
#18000
b10010 (
b10010 )
b1110 #
1+
#19000
b10011 (
b10011 )
b1010 #
0+
#20000
b10100 (
b10100 )
b1110 #
1+
#21000
b10101 (
b10101 )
b10 #
0+
0*
b10 .
b10 $
#22000
b10 &
b10110 (
b10110 )
b1011 #
1-
1*
b0 .
b0 $
#23000
b0 &
b10111 (
b10111 )
b1001 #
0,
#24000
b11000 (
b11000 )
b1100 #
0-
1+
#25000
b11001 (
b11001 )
b111 #
1-
1,
0*
b1 .
b1 $
#26000
b1 &
b11010 (
b11010 )
