Verision1/02_rlt/LOPD_4bit.sv
module LOPD_4bit(
    input logic [3:0]       i_data  ,
    output logic [1:0]      o_pos_one,
    output logic            o_zero_flag
);

/////////////////// LDO ///////////////////
// D[3] | D[2] | D[1] | D[0] |PO[3] | PO[2] | PO[1] | PO[0] | ZERO_FLAG |
//   0  |   0  |   0  |   0  |  0   |   0   |   0   |   0   |     1     |
//   0  |   0  |   0  |   1  |  0   |   0   |   0   |   1   |     0     |
//   0  |   0  |   1  |   X  |  0   |   0   |   1   |   0   |     0     |
//   0  |   1  |   X  |   X  |  0   |   1   |   0   |   0   |     0     |
//   1  |   X  |   X  |   X  |  1   |   0   |   0   |   0   |     0     |
/////////////////// LDOD ///////////////////
// D[3] | D[2] | D[1] | D[0] | PO[1] | PO[0] | ZERO_FLAG |
//   0  |   0  |   0  |   0  |   0   |   0   |     1     |
//   0  |   0  |   0  |   1  |   0   |   0   |     0     |
//   0  |   0  |   1  |   X  |   0   |   1   |     0     |
//   0  |   1  |   X  |   X  |   1   |   0   |     0     |
//   1  |   X  |   X  |   X  |   1   |   1   |     0     |

// assign o_zero_flag = ~( (i_data[3] | i_data[2]) | (i_data[1] | i_data[0]) ) ;
assign o_zero_flag = ~( |i_data );  // Toán tử reduction OR
assign o_pos_one[1] = i_data[3] | i_data[2];
assign o_pos_one[0] = ((~(i_data[3] | i_data[2])) & (i_data[1])) |  (i_data[3]);

endmodule

Verision1/03_verif/SubModule/LOPD_UNIT/LOPD_4BIT/tb_LOPD_4bit.sv
`timescale 1ns/1ps

module tb_LOPD_4bit();

    // ================= PARAMETERS ================= //
    parameter SIZE_DATA = 4;
    parameter SIZE_POS  = 2; // log2(4) = 2

    // ================= SIGNALS ================= //
    logic [SIZE_DATA-1:0] i_data;
    logic [SIZE_POS-1:0]  o_pos_one;
    logic                 o_zero_flag;

    logic [SIZE_POS-1:0]  w_expect_pos;
    logic                 w_expect_zero;

    int test_count = 0;
    int test_pass  = 0;

    // ================= DUT ================= //
    LOPD_4bit DUT (
        .i_data(i_data),
        .o_pos_one(o_pos_one),
        .o_zero_flag(o_zero_flag)
    );

    // ================= DUMP WAVE ================= //
    initial begin
        $dumpfile("tb_LOPD_4bit.vcd");
        $dumpvars(0, tb_LOPD_4bit);
    end

    // ================= FUNCTION: Reference Model ================= //
    function automatic void f_find_LOPD(
        input  logic [SIZE_DATA-1:0] f_i_data,
        output logic [SIZE_POS-1:0]  f_o_pos_one,
        output logic                 f_o_zero_flag
    );
        int pos;
        begin
            if (f_i_data == 0) begin
                f_o_pos_one   = 0;
                f_o_zero_flag = 1;
            end else begin
                // find position of leading '1'
                for (pos = SIZE_DATA-1; pos >= 0; pos--) begin
                    if (f_i_data[pos]) begin
                        f_o_pos_one   = SIZE_DATA-1 - pos; // distance from MSB
                        f_o_zero_flag = 0;
                        break;
                    end
                end
            end
        end
    endfunction

    // ================= TASK: Display & Compare ================= //
    task automatic Check_Result(
        input string t_name,
        input logic [SIZE_DATA-1:0] t_data,
        input logic [SIZE_POS-1:0] exp_pos,
        input logic                 exp_zero,
        input logic [SIZE_POS-1:0] dut_pos,
        input logic                 dut_zero
    );
        string result;
        result = ((exp_pos == dut_pos) && (exp_zero == dut_zero)) ? "PASS" : "FAIL";
        $display("[%s] data=%b => expect(pos=%0d, zero=%b), dut(pos=%0d, zero=%b) => %s",
                 t_name, t_data, exp_pos, exp_zero, dut_pos, dut_zero, result);
        test_count++;
        if (result == "PASS") test_pass++;
    endtask

    // ================= TEST SEQUENCE ================= //
    initial begin
        $display("\n=== START 4-bit LEADING ONE POSITION DETECTOR TEST ===\n");

        // --- Deterministic test patterns ---
        for (int i = 0; i < 16; i++) begin
            i_data = i[SIZE_DATA-1:0];
            #1;
            f_find_LOPD(i_data, w_expect_pos, w_expect_zero);
            Check_Result("Fixed", i_data, w_expect_pos, w_expect_zero, o_pos_one, o_zero_flag);
        end

        // --- Random test cases ---
        repeat (10) begin
            i_data = $urandom_range(0, (1 << SIZE_DATA) - 1);
            #1;
            f_find_LOPD(i_data, w_expect_pos, w_expect_zero);
            Check_Result("Random", i_data, w_expect_pos, w_expect_zero, o_pos_one, o_zero_flag);
        end

        // --- Summary ---
        #5;
        $display("\n==================================");
        $display("========== TEST SUMMARY ==========");
        $display("Total test cases: %6d", test_count);
        $display("Passed          : %6d", test_pass);
        $display("Failed          : %6d", test_count - test_pass);
        $display("Pass rate       : %0.2f%%", (test_pass * 100.0) / test_count);
        $display("==================================\n");

        #10;
        $finish;
    end

endmodule

Verision1/03_verif/SubModule/LOPD_UNIT/LOPD_4BIT/Verilator/tb_LOPD_4bit.vcd
$version Generated by VerilatedVcd $end
$timescale 1ps $end
 $scope module TOP $end
  $scope module tb_LOPD_4bit $end
   $var wire 32 + SIZE_DATA [31:0] $end
   $var wire 32 , SIZE_POS [31:0] $end
   $var wire 4 # i_data [3:0] $end
   $var wire 2 $ o_pos_one [1:0] $end
   $var wire 1 % o_zero_flag $end
   $var wire 2 & w_expect_pos [1:0] $end
   $var wire 1 ' w_expect_zero $end
   $var wire 32 ( test_count [31:0] $end
   $var wire 32 ) test_pass [31:0] $end
   $scope module DUT $end
    $var wire 4 # i_data [3:0] $end
    $var wire 2 $ o_pos_one [1:0] $end
    $var wire 1 % o_zero_flag $end
   $upscope $end
   $scope module unnamedblk1 $end
    $var wire 32 * i [31:0] $end
   $upscope $end
  $upscope $end
 $upscope $end
$enddefinitions $end


#0
b0000 #
b00 $
1%
b00 &
0'
b00000000000000000000000000000000 (
b00000000000000000000000000000000 )
b00000000000000000000000000000000 *
b00000000000000000000000000000100 +
b00000000000000000000000000000010 ,
#1000
b0001 #
b11 $
0%
1'
b00000000000000000000000000000001 (
b00000000000000000000000000000001 )
b00000000000000000000000000000001 *
#2000
b0010 #
b10 $
b11 &
0'
b00000000000000000000000000000010 (
b00000000000000000000000000000010 )
b00000000000000000000000000000010 *
#3000
b0011 #
b10 &
b00000000000000000000000000000011 (
b00000000000000000000000000000011 )
b00000000000000000000000000000011 *
#4000
b0100 #
b01 $
b00000000000000000000000000000100 (
b00000000000000000000000000000100 )
b00000000000000000000000000000100 *
#5000
b0101 #
b01 &
b00000000000000000000000000000101 (
b00000000000000000000000000000101 )
b00000000000000000000000000000101 *
#6000
b0110 #
b00000000000000000000000000000110 (
b00000000000000000000000000000110 )
b00000000000000000000000000000110 *
#7000
b0111 #
b00000000000000000000000000000111 (
b00000000000000000000000000000111 )
b00000000000000000000000000000111 *
#8000
b1000 #
b00 $
b00000000000000000000000000001000 (
b00000000000000000000000000001000 )
b00000000000000000000000000001000 *
#9000
b1001 #
b00 &
b00000000000000000000000000001001 (
b00000000000000000000000000001001 )
b00000000000000000000000000001001 *
#10000
b1010 #
b00000000000000000000000000001010 (
b00000000000000000000000000001010 )
b00000000000000000000000000001010 *
#11000
b1011 #
b00000000000000000000000000001011 (
b00000000000000000000000000001011 )
b00000000000000000000000000001011 *
#12000
b1100 #
b00000000000000000000000000001100 (
b00000000000000000000000000001100 )
b00000000000000000000000000001100 *
#13000
b1101 #
b00000000000000000000000000001101 (
b00000000000000000000000000001101 )
b00000000000000000000000000001101 *
#14000
b1110 #
b00000000000000000000000000001110 (
b00000000000000000000000000001110 )
b00000000000000000000000000001110 *
#15000
b1111 #
b00000000000000000000000000001111 (
b00000000000000000000000000001111 )
b00000000000000000000000000001111 *
#16000
b0100 #
b01 $
b00000000000000000000000000010000 (
b00000000000000000000000000010000 )
b00000000000000000000000000010000 *
#17000
b1100 #
b00 $
b01 &
b00000000000000000000000000010001 (
b00000000000000000000000000010001 )
#18000
b0010 #
b10 $
b00 &
b00000000000000000000000000010010 (
b00000000000000000000000000010010 )
#19000
b0100 #
b01 $
b10 &
b00000000000000000000000000010011 (
b00000000000000000000000000010011 )
#20000
b1000 #
b00 $
b01 &
b00000000000000000000000000010100 (
b00000000000000000000000000010100 )
#21000
b1100 #
b00 &
b00000000000000000000000000010101 (
b00000000000000000000000000010101 )
#22000
b0110 #
b01 $
b00000000000000000000000000010110 (
b00000000000000000000000000010110 )
#23000
b0100 #
b01 &
b00000000000000000000000000010111 (
b00000000000000000000000000010111 )
#24000
b0111 #
b00000000000000000000000000011000 (
b00000000000000000000000000011000 )
#25000
b0011 #
b10 $
b00000000000000000000000000011001 (
b00000000000000000000000000011001 )
#26000
b10 &
b00000000000000000000000000011010 (
b00000000000000000000000000011010 )
