Verision1/02_rlt/LOPD_4bit.sv
module LOPD_4bit(
    input logic [3:0]       i_data  ,
    output logic [1:0]      o_pos_one,
    output logic            o_zero_flag
);

/////////////////// LDO ///////////////////
// D[3] | D[2] | D[1] | D[0] |PO[3] | PO[2] | PO[1] | PO[0] | ZERO_FLAG |
//   0  |   0  |   0  |   0  |  0   |   0   |   0   |   0   |     1     |
//   0  |   0  |   0  |   1  |  0   |   0   |   0   |   1   |     0     |
//   0  |   0  |   1  |   X  |  0   |   0   |   1   |   0   |     0     |
//   0  |   1  |   X  |   X  |  0   |   1   |   0   |   0   |     0     |
//   1  |   X  |   X  |   X  |  1   |   0   |   0   |   0   |     0     |
/////////////////// LDOD ///////////////////
// D[3] | D[2] | D[1] | D[0] | PO[1] | PO[0] | ZERO_FLAG |
//   0  |   0  |   0  |   0  |   0   |   0   |     1     |
//   0  |   0  |   0  |   1  |   0   |   0   |     0     |
//   0  |   0  |   1  |   X  |   0   |   1   |     0     |
//   0  |   1  |   X  |   X  |   1   |   0   |     0     |
//   1  |   X  |   X  |   X  |   1   |   1   |     0     |

// assign o_zero_flag = ~( (i_data[3] | i_data[2]) | (i_data[1] | i_data[0]) ) ;
assign o_zero_flag = ~( |i_data );  // Toán tử reduction OR
assign o_pos_one[1] = i_data[3] | i_data[2];
assign o_pos_one[0] = ((~(i_data[3] | i_data[2])) & (i_data[1])) |  (i_data[3]);

endmodule

Version_Final/02_rlt/LOPD_8bit.sv
module LOPD_8bit(
    input logic [7:0]       i_data  ,
    output logic [2:0]      o_pos_one,
    output logic            o_zero_flag
);

////////////////////////////////////////////////////////////
// LOPD_4bit_unit_0
////////////////////////////////////////////////////////////
logic w_zero_flag_0;
logic [1:0] w_pos_one_0;
LOPD_4bit LOPD_4bit_unit_0 (
    .i_data         (i_data[3:0]),
    .o_pos_one      (w_pos_one_0),
    .o_zero_flag    (w_zero_flag_0)
);

////////////////////////////////////////////////////////////
// LOPD_4bit_unit_1
////////////////////////////////////////////////////////////
logic w_zero_flag_1;
logic [1:0] w_pos_one_1;
LOPD_4bit LOPD_4bit_unit_1 (
    .i_data         (i_data[7:4]),
    .o_pos_one      (w_pos_one_1),
    .o_zero_flag    (w_zero_flag_1)
);

////////////////////////////////////////////////////////////
// LOD_8bit_unit
////////////////////////////////////////////////////////////
logic [2:0] w_o_pos_one;
assign o_zero_flag = w_zero_flag_0 & w_zero_flag_1;
assign w_o_pos_one[2] = w_zero_flag_1;
assign w_o_pos_one[1] = w_zero_flag_1 ? w_pos_one_0[1] : w_pos_one_1[1];
assign w_o_pos_one[0] = w_zero_flag_1 ? w_pos_one_0[0] : w_pos_one_1[0];
// assign w_o_pos_one[0] = (~i_data[7] & ~i_data[5] & ~i_data[3] & ~i_data[1] & i_data[0]) | (~i_data[7] & ~i_data[5] & ~i_data[3] & i_data[2]) | (~i_data[7] & ~i_data[5] & i_data[4]) | (~i_data[7] & i_data[6]);
// assign w_o_pos_one[1] = (~i_data[7] & ~i_data[6] & ~i_data[3] & ~i_data[2] & i_data[0]) | (~i_data[7] & ~i_data[6] & ~i_data[3] & ~i_data[2] & i_data[1]) | (~i_data[7] & ~i_data[6] & i_data[4]) | (~i_data[7] & ~i_data[6] & i_data[5]);
// assign w_o_pos_one[2] = (~i_data[7] & ~i_data[6] & ~i_data[5] & ~i_data[4] & i_data[0]) | (~i_data[7] & ~i_data[6] & ~i_data[5] & ~i_data[4] & i_data[1]) | (~i_data[7] & ~i_data[6] & ~i_data[5] & ~i_data[4] & i_data[2]) | (~i_data[7] & ~i_data[6] & ~i_data[5] & ~i_data[4] & i_data[3]);
// assign o_zero_flag = ~(i_data[7] | i_data[6] | i_data[5] | i_data[4] | i_data[3] | i_data[2] | i_data[1] | i_data[0] );
assign o_pos_one = o_zero_flag ? '0 : w_o_pos_one;
endmodule

Version_Final/03_verif/SubModule/LOPD_UNIT/LOPD_24BIT/Verilator/coverage/annotated_src/LOPD_16bit.sv
//      // verilator_coverage annotation
        module LOPD_16bit(
 000036     input logic [15:0]       i_data  ,
%000002     output logic [3:0]      o_pos_one,
%000002     output logic            o_zero_flag
        );
        
        ////////////////////////////////////////////////////////////
        // LOPD_8bit_unit_0
        ////////////////////////////////////////////////////////////
 000012 logic [2:0]         w_pos_one_0;  
%000004 logic               w_zero_flag_0;
        LOPD_8bit LOPD_8bit_unit_0(
            .i_data         (i_data[7:0]),
            .o_pos_one      (w_pos_one_0),
            .o_zero_flag    (w_zero_flag_0)
        );
        ////////////////////////////////////////////////////////////
        // LOPD_8bit_unit_1
        ////////////////////////////////////////////////////////////
 000010 logic [2:0]         w_pos_one_1;  
%000002 logic               w_zero_flag_1;
        LOPD_8bit LOPD_8bit_unit_1(
            .i_data         (i_data[15:8]),
            .o_pos_one      (w_pos_one_1),
            .o_zero_flag    (w_zero_flag_1)
        );
        
        ////////////////////////////////////////////////////////////
        // LOD_16bit_unit
        ////////////////////////////////////////////////////////////
%000002 logic [3:0] w_o_pos_one;
        assign o_zero_flag = w_zero_flag_0 & w_zero_flag_1;
        assign w_o_pos_one[3] = w_zero_flag_1;
        assign w_o_pos_one[2] = w_zero_flag_1 ? w_pos_one_0[2] : w_pos_one_1[2];
        assign w_o_pos_one[1] = w_zero_flag_1 ? w_pos_one_0[1] : w_pos_one_1[1];
        assign w_o_pos_one[0] = w_zero_flag_1 ? w_pos_one_0[0] : w_pos_one_1[0];
        assign o_pos_one = o_zero_flag ? '0 : w_o_pos_one;
        
        endmodule

Verision1/02_rlt/LOPD_24bit.sv
module LOPD_24bit #(
    parameter SIZE_DATA     = 24    ,
    parameter SIZE_LOPD     = 5      
)(
    input logic [SIZE_DATA-1:0]     i_data          ,
    output logic [SIZE_LOPD-1:0]    o_one_position  ,
    output logic                    o_zero_flag      
);

logic [15:0]     LOPD16_i_data;
assign LOPD16_i_data = i_data[23:8];
logic [3:0]      LOPD16_o_pos_one;
logic            LOPD16_o_zero_flag;
LOPD_16bit LOPD_16bit_UNIT_MSB (
    .i_data             (LOPD16_i_data),
    .o_pos_one          (LOPD16_o_pos_one),
    .o_zero_flag        (LOPD16_o_zero_flag)
);

logic [7:0]      LOPD8_i_data;
assign LOPD8_i_data = i_data[7:0];
logic [2:0]      LOPD8_o_pos_one;
logic            LOPD8_o_zero_flag;
LOPD_8bit LOPD_8bit_UNIT_LSB (
    .i_data             (LOPD8_i_data),
    .o_pos_one          (LOPD8_o_pos_one),
    .o_zero_flag        (LOPD8_o_zero_flag)
);

logic [SIZE_LOPD-1:0]        w_o_one_position;
assign o_zero_flag         = LOPD16_o_zero_flag & LOPD8_o_zero_flag;
assign w_o_one_position[4] = LOPD16_o_zero_flag;
assign w_o_one_position[3] = LOPD16_o_zero_flag ? 1'b0               : LOPD16_o_pos_one[3];
assign w_o_one_position[2] = LOPD16_o_zero_flag ? LOPD8_o_pos_one[2] : LOPD16_o_pos_one[2];
assign w_o_one_position[1] = LOPD16_o_zero_flag ? LOPD8_o_pos_one[1] : LOPD16_o_pos_one[1];
assign w_o_one_position[0] = LOPD16_o_zero_flag ? LOPD8_o_pos_one[0] : LOPD16_o_pos_one[0];
assign o_one_position = o_zero_flag ? '0 : w_o_one_position;
endmodule

Version_Final/03_verif/SubModule/LOPD_UNIT/LOPD_24BIT/tb_LOPD_24bit.sv
`timescale 1ns/1ps

module tb_LOPD_24bit();

    // ================= PARAMETERS ================= //
    parameter SIZE_DATA = 24;
    parameter SIZE_POS  = 5; // log2(24) = 5

    // ================= SIGNALS ================= //
    logic i_clk;
    logic [SIZE_DATA-1:0] i_data;
    logic [SIZE_POS-1:0]  o_pos_one;
    logic                 o_zero_flag;

    logic [SIZE_POS-1:0]  w_expect_pos;
    logic                 w_expect_zero;

    int test_count = 0;
    int test_pass  = 0;

    // ================= DUT ================= //
    LOPD_24bit #(
        .SIZE_DATA  (SIZE_DATA),
        .SIZE_LOPD  (SIZE_POS)
    ) DUT (
        .i_data         (i_data),
        .o_one_position (o_pos_one),
        .o_zero_flag    (o_zero_flag)
    );

    // ================= DUMP WAVE ================= //
    initial begin
        i_clk = 1'b0;
        forever begin
            #5 i_clk = ~i_clk;
        end
    end
    initial begin
        $dumpfile("tb_LOPD_24bit.vcd");
        $dumpvars(0, tb_LOPD_24bit);
    end

    // ================= FUNCTION: Reference Model ================= //
    function automatic void f_find_LOPD(
        input  logic [SIZE_DATA-1:0] f_i_data,
        output logic [SIZE_POS-1:0]  f_o_pos_one,
        output logic                 f_o_zero_flag
    );
        int pos;
        begin
            if (f_i_data == 0) begin
                f_o_pos_one   = 0;
                f_o_zero_flag = 1;
            end else begin
                // Find position of leading '1' from MSB → LSB
                for (pos = SIZE_DATA-1; pos >= 0; pos--) begin
                    if (f_i_data[pos]) begin
                        f_o_pos_one   = SIZE_DATA-1 - pos; // encode distance from MSB
                        f_o_zero_flag = 0;
                        break;
                    end
                end
            end
        end
    endfunction

    // ================= TASK: Display & Compare ================= //
    task automatic Check_Result(
        input string t_name,
        input logic [SIZE_DATA-1:0] t_data,
        input logic [SIZE_POS-1:0]  exp_pos,
        input logic                 exp_zero,
        input logic [SIZE_POS-1:0]  dut_pos,
        input logic                 dut_zero
    );
        string result;
        result = ((exp_pos == dut_pos) && (exp_zero == dut_zero)) ? "PASS" : "FAIL";
        $display("[%s] data=%b => expect(pos=%0d, zero=%b), dut(pos=%0d, zero=%b) => %s",
                 t_name, t_data, exp_pos, exp_zero, dut_pos, dut_zero, result);
        test_count++;
        if (result == "PASS") test_pass++;
    endtask

    // ================= TEST SEQUENCE ================= //
    int bit_pos;
    initial begin
        $display("\n=== START 8-bit LEADING ONE POSITION DETECTOR TEST ===\n");
        
        @(posedge i_clk);
        #1;
        i_data = 24'h0;
        @(negedge i_clk);
        f_find_LOPD(i_data, w_expect_pos, w_expect_zero);
        Check_Result("Zero", i_data, w_expect_pos, w_expect_zero, o_pos_one, o_zero_flag);

        // --- Deterministic test patterns (0 → 255) ---
        bit_pos = 1;
        repeat (24) begin
            @(posedge i_clk);
            #1;
            i_data  = bit_pos;
            @(negedge i_clk);
            f_find_LOPD(i_data, w_expect_pos, w_expect_zero);
            #1;
            Check_Result("Direcly", i_data, w_expect_pos, w_expect_zero, o_pos_one, o_zero_flag);
            bit_pos = bit_pos << 1'b1;
        end

        // --- Random test cases ---
        repeat (100) begin
            i_data = $urandom_range(0, 16777215);
            #1;
            f_find_LOPD(i_data, w_expect_pos, w_expect_zero);
            Check_Result("Random", i_data, w_expect_pos, w_expect_zero, o_pos_one, o_zero_flag);
        end

        // --- Summary ---
        #5;
        $display("\n==================================");
        $display("========== TEST SUMMARY ==========");
        $display("Total test cases: %6d", test_count);
        $display("Passed          : %6d", test_pass);
        $display("Failed          : %6d", test_count - test_pass);
        $display("Pass rate       : %0.2f%%", (test_pass * 100.0) / test_count);
        $display("==================================\n");

        #10;
        $finish;
    end

endmodule

Version_Final/03_verif/SubModule/LOPD_UNIT/LOPD_24BIT/Verilator/tb_LOPD_24bit.vcd
$version Generated by VerilatedVcd $end
$timescale 1ps $end
 $scope module TOP $end
  $scope module tb_LOPD_24bit $end
   $var wire 32 O SIZE_DATA [31:0] $end
   $var wire 32 P SIZE_POS [31:0] $end
   $var wire 1 N i_clk $end
   $var wire 24 # i_data [23:0] $end
   $var wire 5 3 o_pos_one [4:0] $end
   $var wire 1 4 o_zero_flag $end
   $var wire 5 $ w_expect_pos [4:0] $end
   $var wire 1 % w_expect_zero $end
   $var wire 32 & test_count [31:0] $end
   $var wire 32 ' test_pass [31:0] $end
   $var wire 32 ( bit_pos [31:0] $end
   $scope module DUT $end
    $var wire 32 O SIZE_DATA [31:0] $end
    $var wire 32 P SIZE_LOPD [31:0] $end
    $var wire 24 # i_data [23:0] $end
    $var wire 5 3 o_one_position [4:0] $end
    $var wire 1 4 o_zero_flag $end
    $var wire 16 ) LOPD16_i_data [15:0] $end
    $var wire 4 5 LOPD16_o_pos_one [3:0] $end
    $var wire 1 6 LOPD16_o_zero_flag $end
    $var wire 8 * LOPD8_i_data [7:0] $end
    $var wire 3 7 LOPD8_o_pos_one [2:0] $end
    $var wire 1 8 LOPD8_o_zero_flag $end
    $var wire 5 9 w_o_one_position [4:0] $end
    $scope module LOPD_16bit_UNIT_MSB $end
     $var wire 16 ) i_data [15:0] $end
     $var wire 4 5 o_pos_one [3:0] $end
     $var wire 1 6 o_zero_flag $end
     $var wire 3 : w_pos_one_0 [2:0] $end
     $var wire 1 ; w_zero_flag_0 $end
     $var wire 3 < w_pos_one_1 [2:0] $end
     $var wire 1 = w_zero_flag_1 $end
     $var wire 4 > w_o_pos_one [3:0] $end
     $scope module LOPD_8bit_unit_0 $end
      $var wire 8 + i_data [7:0] $end
      $var wire 3 : o_pos_one [2:0] $end
      $var wire 1 ; o_zero_flag $end
      $var wire 1 ? w_zero_flag_0 $end
      $var wire 2 @ w_pos_one_0 [1:0] $end
      $var wire 1 A w_zero_flag_1 $end
      $var wire 2 B w_pos_one_1 [1:0] $end
      $var wire 3 C w_o_pos_one [2:0] $end
      $scope module LOPD_4bit_unit_0 $end
       $var wire 4 , i_data [3:0] $end
       $var wire 2 @ o_pos_one [1:0] $end
       $var wire 1 ? o_zero_flag $end
      $upscope $end
      $scope module LOPD_4bit_unit_1 $end
       $var wire 4 - i_data [3:0] $end
       $var wire 2 B o_pos_one [1:0] $end
       $var wire 1 A o_zero_flag $end
      $upscope $end
     $upscope $end
     $scope module LOPD_8bit_unit_1 $end
      $var wire 8 . i_data [7:0] $end
      $var wire 3 < o_pos_one [2:0] $end
      $var wire 1 = o_zero_flag $end
      $var wire 1 D w_zero_flag_0 $end
      $var wire 2 E w_pos_one_0 [1:0] $end
      $var wire 1 F w_zero_flag_1 $end
      $var wire 2 G w_pos_one_1 [1:0] $end
      $var wire 3 H w_o_pos_one [2:0] $end
      $scope module LOPD_4bit_unit_0 $end
       $var wire 4 / i_data [3:0] $end
       $var wire 2 E o_pos_one [1:0] $end
       $var wire 1 D o_zero_flag $end
      $upscope $end
      $scope module LOPD_4bit_unit_1 $end
       $var wire 4 0 i_data [3:0] $end
       $var wire 2 G o_pos_one [1:0] $end
       $var wire 1 F o_zero_flag $end
      $upscope $end
     $upscope $end
    $upscope $end
    $scope module LOPD_8bit_UNIT_LSB $end
     $var wire 8 * i_data [7:0] $end
     $var wire 3 7 o_pos_one [2:0] $end
     $var wire 1 8 o_zero_flag $end
     $var wire 1 I w_zero_flag_0 $end
     $var wire 2 J w_pos_one_0 [1:0] $end
     $var wire 1 K w_zero_flag_1 $end
     $var wire 2 L w_pos_one_1 [1:0] $end
     $var wire 3 M w_o_pos_one [2:0] $end
     $scope module LOPD_4bit_unit_0 $end
      $var wire 4 1 i_data [3:0] $end
      $var wire 2 J o_pos_one [1:0] $end
      $var wire 1 I o_zero_flag $end
     $upscope $end
     $scope module LOPD_4bit_unit_1 $end
      $var wire 4 2 i_data [3:0] $end
      $var wire 2 L o_pos_one [1:0] $end
      $var wire 1 K o_zero_flag $end
     $upscope $end
    $upscope $end
   $upscope $end
  $upscope $end
 $upscope $end
$enddefinitions $end


#0
b000000000000000000000000 #
b00000 $
0%
b00000000000000000000000000000000 &
b00000000000000000000000000000000 '
b00000000000000000000000000000000 (
b0000000000000000 )
b00000000 *
b00000000 +
b0000 ,
b0000 -
b00000000 .
b0000 /
b0000 0
b0000 1
b0000 2
b00000 3
14
b0000 5
16
b000 7
18
b10000 9
b000 :
1;
b000 <
1=
b1000 >
1?
b00 @
1A
b00 B
b100 C
1D
b00 E
1F
b00 G
b100 H
1I
b00 J
1K
b00 L
b100 M
0N
b00000000000000000000000000011000 O
b00000000000000000000000000000101 P
#5000
1N
#6000
1%
b00000000000000000000000000000001 &
b00000000000000000000000000000001 '
b00000000000000000000000000000001 (
#10000
0N
#15000
1N
#16000
b000000000000000000000001 #
b00000001 *
b0001 1
b10111 3
04
b111 7
08
b10111 9
0I
b11 J
b111 M
#20000
b10111 $
0%
0N
#21000
b00000000000000000000000000000010 &
b00000000000000000000000000000010 '
b00000000000000000000000000000010 (
#25000
1N
#26000
b000000000000000000000010 #
b00000010 *
b0010 1
b10110 3
b110 7
b10110 9
b10 J
b110 M
#30000
b10110 $
0N
#31000
b00000000000000000000000000000011 &
b00000000000000000000000000000011 '
b00000000000000000000000000000100 (
#35000
1N
#36000
b000000000000000000000100 #
b00000100 *
b0100 1
b10101 3
b101 7
b10101 9
b01 J
b101 M
#40000
b10101 $
0N
#41000
b00000000000000000000000000000100 &
b00000000000000000000000000000100 '
b00000000000000000000000000001000 (
#45000
1N
#46000
b000000000000000000001000 #
b00001000 *
b1000 1
b10100 3
b100 7
b10100 9
b00 J
b100 M
#50000
b10100 $
0N
#51000
b00000000000000000000000000000101 &
b00000000000000000000000000000101 '
b00000000000000000000000000010000 (
#55000
1N
#56000
b000000000000000000010000 #
b00010000 *
b0000 1
b0001 2
b10011 3
b011 7
b10011 9
1I
0K
b11 L
b011 M
#60000
b10011 $
0N
#61000
b00000000000000000000000000000110 &
b00000000000000000000000000000110 '
b00000000000000000000000000100000 (
#65000
1N
#66000
b000000000000000000100000 #
b00100000 *
b0010 2
b10010 3
b010 7
b10010 9
b10 L
b010 M
#70000
b10010 $
0N
#71000
b00000000000000000000000000000111 &
b00000000000000000000000000000111 '
b00000000000000000000000001000000 (
#75000
1N
#76000
b000000000000000001000000 #
b01000000 *
b0100 2
b10001 3
b001 7
b10001 9
b01 L
b001 M
#80000
b10001 $
0N
#81000
b00000000000000000000000000001000 &
b00000000000000000000000000001000 '
b00000000000000000000000010000000 (
#85000
1N
#86000
b000000000000000010000000 #
b10000000 *
b1000 2
b10000 3
b000 7
b10000 9
b00 L
b000 M
#90000
b10000 $
0N
#91000
b00000000000000000000000000001001 &
b00000000000000000000000000001001 '
b00000000000000000000000100000000 (
#95000
1N
#96000
b000000000000000100000000 #
b0000000000000001 )
b00000000 *
b00000001 +
b0001 ,
b0000 2
b01111 3
b1111 5
06
18
b01111 9
b111 :
0;
b1111 >
0?
b11 @
b111 C
1K
b100 M
#100000
b01111 $
0N
#101000
b00000000000000000000000000001010 &
b00000000000000000000000000001010 '
b00000000000000000000001000000000 (
#105000
1N
#106000
b000000000000001000000000 #
b0000000000000010 )
b00000010 +
b0010 ,
b01110 3
b1110 5
b01110 9
b110 :
b1110 >
b10 @
b110 C
#110000
b01110 $
0N
#111000
b00000000000000000000000000001011 &
b00000000000000000000000000001011 '
b00000000000000000000010000000000 (
#115000
1N
#116000
b000000000000010000000000 #
b0000000000000100 )
b00000100 +
b0100 ,
b01101 3
b1101 5
b01101 9
b101 :
b1101 >
b01 @
b101 C
#120000
b01101 $
0N
#121000
b00000000000000000000000000001100 &
b00000000000000000000000000001100 '
b00000000000000000000100000000000 (
#125000
1N
#126000
b000000000000100000000000 #
b0000000000001000 )
b00001000 +
b1000 ,
b01100 3
b1100 5
b01100 9
b100 :
b1100 >
b00 @
b100 C
#130000
b01100 $
0N
#131000
b00000000000000000000000000001101 &
b00000000000000000000000000001101 '
b00000000000000000001000000000000 (
#135000
1N
#136000
b000000000001000000000000 #
b0000000000010000 )
b00010000 +
b0000 ,
b0001 -
b01011 3
b1011 5
b01011 9
b011 :
b1011 >
1?
0A
b11 B
b011 C
#140000
b01011 $
0N
#141000
b00000000000000000000000000001110 &
b00000000000000000000000000001110 '
b00000000000000000010000000000000 (
#145000
1N
#146000
b000000000010000000000000 #
b0000000000100000 )
b00100000 +
b0010 -
b01010 3
b1010 5
b01010 9
b010 :
b1010 >
b10 B
b010 C
#150000
b01010 $
0N
#151000
b00000000000000000000000000001111 &
b00000000000000000000000000001111 '
b00000000000000000100000000000000 (
#155000
1N
#156000
b000000000100000000000000 #
b0000000001000000 )
b01000000 +
b0100 -
b01001 3
b1001 5
b01001 9
b001 :
b1001 >
b01 B
b001 C
#160000
b01001 $
0N
#161000
b00000000000000000000000000010000 &
b00000000000000000000000000010000 '
b00000000000000001000000000000000 (
#165000
1N
#166000
b000000001000000000000000 #
b0000000010000000 )
b10000000 +
b1000 -
b01000 3
b1000 5
b01000 9
b000 :
b1000 >
b00 B
b000 C
#170000
b01000 $
0N
#171000
b00000000000000000000000000010001 &
b00000000000000000000000000010001 '
b00000000000000010000000000000000 (
#175000
1N
#176000
b000000010000000000000000 #
b0000000100000000 )
b00000000 +
b0000 -
b00000001 .
b0001 /
b00111 3
b0111 5
b00111 9
1;
b111 <
0=
b0111 >
1A
b100 C
0D
b11 E
b111 H
#180000
b00111 $
0N
#181000
b00000000000000000000000000010010 &
b00000000000000000000000000010010 '
b00000000000000100000000000000000 (
#185000
1N
#186000
b000000100000000000000000 #
b0000001000000000 )
b00000010 .
b0010 /
b00110 3
b0110 5
b00110 9
b110 <
b0110 >
b10 E
b110 H
#190000
b00110 $
0N
#191000
b00000000000000000000000000010011 &
b00000000000000000000000000010011 '
b00000000000001000000000000000000 (
#195000
1N
#196000
b000001000000000000000000 #
b0000010000000000 )
b00000100 .
b0100 /
b00101 3
b0101 5
b00101 9
b101 <
b0101 >
b01 E
b101 H
#200000
b00101 $
0N
#201000
b00000000000000000000000000010100 &
b00000000000000000000000000010100 '
b00000000000010000000000000000000 (
#205000
1N
#206000
b000010000000000000000000 #
b0000100000000000 )
b00001000 .
b1000 /
b00100 3
b0100 5
b00100 9
b100 <
b0100 >
b00 E
b100 H
#210000
b00100 $
0N
#211000
b00000000000000000000000000010101 &
b00000000000000000000000000010101 '
b00000000000100000000000000000000 (
#215000
1N
#216000
b000100000000000000000000 #
b0001000000000000 )
b00010000 .
b0000 /
b0001 0
b00011 3
b0011 5
b00011 9
b011 <
b0011 >
1D
0F
b11 G
b011 H
#220000
b00011 $
0N
#221000
b00000000000000000000000000010110 &
b00000000000000000000000000010110 '
b00000000001000000000000000000000 (
#225000
1N
#226000
b001000000000000000000000 #
b0010000000000000 )
b00100000 .
b0010 0
b00010 3
b0010 5
b00010 9
b010 <
b0010 >
b10 G
b010 H
#230000
b00010 $
0N
#231000
b00000000000000000000000000010111 &
b00000000000000000000000000010111 '
b00000000010000000000000000000000 (
#235000
1N
#236000
b010000000000000000000000 #
b0100000000000000 )
b01000000 .
b0100 0
b00001 3
b0001 5
b00001 9
b001 <
b0001 >
b01 G
b001 H
#240000
b00001 $
0N
#241000
b00000000000000000000000000011000 &
b00000000000000000000000000011000 '
b00000000100000000000000000000000 (
#245000
1N
#246000
b100000000000000000000000 #
b1000000000000000 )
b10000000 .
b1000 0
b00000 3
b0000 5
b00000 9
b000 <
b0000 >
b00 G
b000 H
#250000
b00000 $
0N
#251000
b011101100111001111000100 #
b00000000000000000000000000011001 &
b00000000000000000000000000011001 '
b00000001000000000000000000000000 (
b0111011001110011 )
b11000100 *
b01110011 +
b0011 ,
b0111 -
b01110110 .
b0110 /
b0111 0
b0100 1
b1100 2
b00001 3
b0001 5
08
b00001 9
b001 :
0;
b001 <
b0001 >
0?
b10 @
0A
b01 B
b001 C
0D
b01 E
b01 G
b001 H
0I
b01 J
0K
b000 M
#252000
b000111100101110110011100 #
b00001 $
b00000000000000000000000000011010 &
b00000000000000000000000000011010 '
b0001111001011101 )
b10011100 *
b01011101 +
b1101 ,
b0101 -
b00011110 .
b1110 /
b0001 0
b1100 1
b1001 2
b00011 3
b0011 5
b00011 9
b011 <
b0011 >
b00 @
b00 E
b11 G
b011 H
b00 J
#253000
b111111011101010100000010 #
b00011 $
b00000000000000000000000000011011 &
b00000000000000000000000000011011 '
b1111110111010101 )
b00000010 *
b11010101 +
b0101 ,
b1101 -
b11111101 .
b1101 /
b1111 0
b0010 1
b0000 2
b00000 3
b0000 5
b110 7
b00000 9
b000 :
b000 <
b0000 >
b01 @
b00 B
b000 C
b00 G
b000 H
b10 J
1K
b110 M
#254000
b110000101110000011100100 #
b00000 $
b00000000000000000000000000011100 &
b00000000000000000000000000011100 '
b1100001011100000 )
b11100100 *
b11100000 +
b0000 ,
b1110 -
b11000010 .
b0010 /
b1100 0
b0100 1
b1110 2
b000 7
1?
b00 @
b10 E
b01 J
0K
b000 M
#255000
b000101111000001101111000 #
b00000000000000000000000000011101 &
b00000000000000000000000000011101 '
b0001011110000011 )
b01111000 *
b10000011 +
b0011 ,
b1000 -
b00010111 .
b0111 /
b0001 0
b1000 1
b0111 2
b00011 3
b0011 5
b001 7
b00011 9
b011 <
b0011 >
0?
b10 @
b01 E
b11 G
b011 H
b00 J
b01 L
b001 M
1N
#256000
b110101011000111010111100 #
b00011 $
b00000000000000000000000000011110 &
b00000000000000000000000000011110 '
b1101010110001110 )
b10111100 *
b10001110 +
b1110 ,
b11010101 .
b0101 /
b1101 0
b1100 1
b1011 2
b00000 3
b0000 5
b000 7
b00000 9
b000 <
b0000 >
b00 @
b00 G
b000 H
b00 L
b000 M
#257000
b101001001001111010110110 #
b00000 $
b00000000000000000000000000011111 &
b00000000000000000000000000011111 '
b1010010010011110 )
b10110110 *
b10011110 +
b1001 -
b10100100 .
b0100 /
b1010 0
b0110 1
b01 J
#258000
b000101001111111111100100 #
b00000000000000000000000000100000 &
b00000000000000000000000000100000 '
b0001010011111111 )
b11100100 *
b11111111 +
b1111 ,
b1111 -
b00010100 .
b0001 0
b0100 1
b1110 2
b00011 3
b0011 5
b00011 9
b011 <
b0011 >
b11 G
b011 H
#259000
b011011111111001110110111 #
b00011 $
b00000000000000000000000000100001 &
b00000000000000000000000000100001 '
b0110111111110011 )
b10110111 *
b11110011 +
b0011 ,
b01101111 .
b1111 /
b0110 0
b0111 1
b1011 2
b00001 3
b0001 5
b00001 9
b001 <
b0001 >
b10 @
b00 E
b01 G
b001 H
#260000
b110001000111000101010011 #
b00001 $
b00000000000000000000000000100010 &
b00000000000000000000000000100010 '
b1100010001110001 )
b01010011 *
b01110001 +
b0001 ,
b0111 -
b11000100 .
b0100 /
b1100 0
b0011 1
b0101 2
b00000 3
b0000 5
b001 7
b00000 9
b001 :
b000 <
b0000 >
b11 @
b01 B
b001 C
b01 E
b00 G
b000 H
b10 J
b01 L
b001 M
0N
#261000
b100111100001011100100001 #
b00000 $
b00000000000000000000000000100011 &
b00000000000000000000000000100011 '
b1001111000010111 )
b00100001 *
b00010111 +
b0111 ,
b0001 -
b10011110 .
b1110 /
b1001 0
b0001 1
b0010 2
b010 7
b011 :
b01 @
b11 B
b011 C
b00 E
b11 J
b10 L
b010 M
#262000
b100110100111110111100001 #
b00000000000000000000000000100100 &
b00000000000000000000000000100100 '
b1001101001111101 )
b11100001 *
b01111101 +
b1101 ,
b0111 -
b10011010 .
b1010 /
b1110 2
b000 7
b001 :
b00 @
b01 B
b001 C
b00 L
b000 M
#263000
b100011001010111111000101 #
b00000000000000000000000000100101 &
b00000000000000000000000000100101 '
b1000110010101111 )
b11000101 *
b10101111 +
b1111 ,
b1010 -
b10001100 .
b1100 /
b1000 0
b0101 1
b1100 2
b000 :
b00 B
b000 C
b01 J
#264000
b010100111111001110000010 #
b00000000000000000000000000100110 &
b00000000000000000000000000100110 '
b0101001111110011 )
b10000010 *
b11110011 +
b0011 ,
b1111 -
b01010011 .
b0011 /
b0101 0
b0010 1
b1000 2
b00001 3
b0001 5
b00001 9
b001 <
b0001 >
b10 @
b10 E
b01 G
b001 H
b10 J
#265000
b010100011111111101100010 #
b00001 $
b00000000000000000000000000100111 &
b00000000000000000000000000100111 '
b0101000111111111 )
b01100010 *
b11111111 +
b1111 ,
b01010001 .
b0001 /
b0110 2
b001 7
b00 @
b11 E
b01 L
b001 M
1N
#266000
b010110000001011000110101 #
b00000000000000000000000000101000 &
b00000000000000000000000000101000 '
b0101100000010110 )
b00110101 *
b00010110 +
b0110 ,
b0001 -
b01011000 .
b1000 /
b0101 1
b0011 2
b010 7
b011 :
b01 @
b11 B
b011 C
b00 E
b01 J
b10 L
b010 M
#267000
b111110111100100100010010 #
b00000000000000000000000000101001 &
b00000000000000000000000000101001 '
b1111101111001001 )
b00010010 *
b11001001 +
b1001 ,
b1100 -
b11111011 .
b1011 /
b1111 0
b0010 1
b0001 2
b00000 3
b0000 5
b011 7
b00000 9
b000 :
b000 <
b0000 >
b00 @
b00 B
b000 C
b00 G
b000 H
b10 J
b11 L
b011 M
#268000
b111110011010101101010110 #
b00000 $
b00000000000000000000000000101010 &
b00000000000000000000000000101010 '
b1111100110101011 )
b01010110 *
b10101011 +
b1011 ,
b1010 -
b11111001 .
b1001 /
b0110 1
b0101 2
b001 7
b01 J
b01 L
b001 M
#269000
b001100100011101111111101 #
b00000000000000000000000000101011 &
b00000000000000000000000000101011 '
b0011001000111011 )
b11111101 *
b00111011 +
b0011 -
b00110010 .
b0010 /
b0011 0
b1101 1
b1111 2
b00010 3
b0010 5
b000 7
b00010 9
b010 :
b010 <
b0010 >
b10 B
b010 C
b10 E
b10 G
b010 H
b00 J
b00 L
b000 M
#270000
b011010110100000111110100 #
b00010 $
b00000000000000000000000000101100 &
b00000000000000000000000000101100 '
b0110101101000001 )
b11110100 *
b01000001 +
b0001 ,
b0100 -
b01101011 .
b1011 /
b0110 0
b0100 1
b00001 3
b0001 5
b00001 9
b001 :
b001 <
b0001 >
b11 @
b01 B
b001 C
b00 E
b01 G
b001 H
b01 J
0N
#271000
b101011011111010100111011 #
b00001 $
b00000000000000000000000000101101 &
b00000000000000000000000000101101 '
b1010110111110101 )
b00111011 *
b11110101 +
b0101 ,
b1111 -
b10101101 .
b1101 /
b1010 0
b1011 1
b0011 2
b00000 3
b0000 5
b010 7
b00000 9
b000 :
b000 <
b0000 >
b01 @
b00 B
b000 C
b00 G
b000 H
b00 J
b10 L
b010 M
