Verision1/02_rlt/LOPD_4bit.sv
module LOPD_4bit(
    input logic [3:0]       i_data  ,
    output logic [1:0]      o_pos_one,
    output logic            o_zero_flag
);

/////////////////// LDO ///////////////////
// D[3] | D[2] | D[1] | D[0] |PO[3] | PO[2] | PO[1] | PO[0] | ZERO_FLAG |
//   0  |   0  |   0  |   0  |  0   |   0   |   0   |   0   |     1     |
//   0  |   0  |   0  |   1  |  0   |   0   |   0   |   1   |     0     |
//   0  |   0  |   1  |   X  |  0   |   0   |   1   |   0   |     0     |
//   0  |   1  |   X  |   X  |  0   |   1   |   0   |   0   |     0     |
//   1  |   X  |   X  |   X  |  1   |   0   |   0   |   0   |     0     |
/////////////////// LDOD ///////////////////
// D[3] | D[2] | D[1] | D[0] | PO[1] | PO[0] | ZERO_FLAG |
//   0  |   0  |   0  |   0  |   0   |   0   |     1     |
//   0  |   0  |   0  |   1  |   0   |   0   |     0     |
//   0  |   0  |   1  |   X  |   0   |   1   |     0     |
//   0  |   1  |   X  |   X  |   1   |   0   |     0     |
//   1  |   X  |   X  |   X  |   1   |   1   |     0     |

// assign o_zero_flag = ~( (i_data[3] | i_data[2]) | (i_data[1] | i_data[0]) ) ;
assign o_zero_flag = ~( |i_data );  // Toán tử reduction OR
assign o_pos_one[1] = i_data[3] | i_data[2];
assign o_pos_one[0] = ((~(i_data[3] | i_data[2])) & (i_data[1])) |  (i_data[3]);

endmodule

Verision1/02_rlt/LOPD_8bit.sv
module LOPD_8bit(
    input logic [7:0]       i_data  ,
    output logic [2:0]      o_pos_one,
    output logic            o_zero_flag
);

////////////////////////////////////////////////////////////
// LOPD_4bit_unit_0
////////////////////////////////////////////////////////////
logic w_zero_flag_0;
logic [1:0] w_pos_one_0;
LOPD_4bit LOPD_4bit_unit_0 (
    .i_data         (i_data[3:0]),
    .o_pos_one      (w_pos_one_0),
    .o_zero_flag    (w_zero_flag_0)
);

////////////////////////////////////////////////////////////
// LOPD_4bit_unit_1
////////////////////////////////////////////////////////////
logic w_zero_flag_1;
logic [1:0] w_pos_one_1;
LOPD_4bit LOPD_4bit_unit_1 (
    .i_data         (i_data[7:4]),
    .o_pos_one      (w_pos_one_1),
    .o_zero_flag    (w_zero_flag_1)
);

////////////////////////////////////////////////////////////
// LOD_8bit_unit
////////////////////////////////////////////////////////////
logic [2:0] w_o_pos_one;
assign o_zero_flag = w_zero_flag_0 & w_zero_flag_1;
assign w_o_pos_one[2] = w_zero_flag_1;
assign w_o_pos_one[1] = w_zero_flag_1 ? w_pos_one_0[1] : w_pos_one_1[1];
assign w_o_pos_one[0] = w_zero_flag_1 ? w_pos_one_0[0] : w_pos_one_1[0];
assign o_pos_one = o_zero_flag ? '0 : w_o_pos_one;

endmodule

Verision1/03_verif/SubModule/LOPD_UNIT/LOPD_16BIT/Verilator/coverage/annotated_src/LOPD_16bit.sv
//      // verilator_coverage annotation
        module LOPD_16bit(
%000004     input logic [15:0]       i_data  ,
%000002     output logic [3:0]      o_pos_one,
%000002     output logic            o_zero_flag
        );
        
        ////////////////////////////////////////////////////////////
        // LOPD_8bit_unit_0
        ////////////////////////////////////////////////////////////
 000514 logic [2:0]         w_pos_one_0;  
 000512 logic               w_zero_flag_0;
        LOPD_8bit LOPD_8bit_unit_0(
            .i_data         (i_data[7:0]),
            .o_pos_one      (w_pos_one_0),
            .o_zero_flag    (w_zero_flag_0)
        );
        ////////////////////////////////////////////////////////////
        // LOPD_8bit_unit_1
        ////////////////////////////////////////////////////////////
%000002 logic [2:0]         w_pos_one_1;  
%000002 logic               w_zero_flag_1;
        LOPD_8bit LOPD_8bit_unit_1(
            .i_data         (i_data[15:8]),
            .o_pos_one      (w_pos_one_1),
            .o_zero_flag    (w_zero_flag_1)
        );
        
        ////////////////////////////////////////////////////////////
        // LOD_16bit_unit
        ////////////////////////////////////////////////////////////
%000002 logic [3:0] w_o_pos_one;
        assign o_zero_flag = w_zero_flag_0 & w_zero_flag_1;
        assign w_o_pos_one[3] = w_zero_flag_1;
        assign w_o_pos_one[2] = w_zero_flag_1 ? w_pos_one_0[2] : w_pos_one_1[2];
        assign w_o_pos_one[1] = w_zero_flag_1 ? w_pos_one_0[1] : w_pos_one_1[1];
        assign w_o_pos_one[0] = w_zero_flag_1 ? w_pos_one_0[0] : w_pos_one_1[0];
        assign o_pos_one = o_zero_flag ? '0 : w_o_pos_one;
        
        endmodule

Verision1/03_verif/SubModule/LOPD_UNIT/LOPD_24BIT/Verilator/coverage/annotated_src/LOPD_24bit.sv
//      // verilator_coverage annotation
        module LOPD_24bit #(
            parameter SIZE_DATA     = 24    ,
            parameter SIZE_LOPD     = 5      
        )(
 000036     input logic [SIZE_DATA-1:0]     i_data          ,
%000002     output logic [SIZE_LOPD-1:0]    o_one_position  ,
%000002     output logic                    o_zero_flag      
        );
        
 000036 logic [15:0]     LOPD16_i_data;
        assign LOPD16_i_data = i_data[23:8];
%000002 logic [3:0]      LOPD16_o_pos_one;
%000002 logic            LOPD16_o_zero_flag;
        LOPD_16bit LOPD_16bit_UNIT_MSB (
            .i_data             (LOPD16_i_data),
            .o_pos_one          (LOPD16_o_pos_one),
            .o_zero_flag        (LOPD16_o_zero_flag)
        );
        
 000044 logic [7:0]      LOPD8_i_data;
        assign LOPD8_i_data = i_data[7:0];
 000013 logic [2:0]      LOPD8_o_pos_one;
%000004 logic            LOPD8_o_zero_flag;
        LOPD_8bit LOPD_8bit_UNIT_LSB (
            .i_data             (LOPD8_i_data),
            .o_pos_one          (LOPD8_o_pos_one),
            .o_zero_flag        (LOPD8_o_zero_flag)
        );
        
%000002 logic [SIZE_LOPD-1:0]        w_o_one_position;
        assign o_zero_flag         = LOPD16_o_zero_flag & LOPD8_o_zero_flag;
        assign w_o_one_position[4] = LOPD16_o_zero_flag;
        assign w_o_one_position[3] = LOPD16_o_zero_flag ? 1'b0               : LOPD16_o_pos_one[3];
        assign w_o_one_position[2] = LOPD16_o_zero_flag ? LOPD8_o_pos_one[2] : LOPD16_o_pos_one[2];
        assign w_o_one_position[1] = LOPD16_o_zero_flag ? LOPD8_o_pos_one[1] : LOPD16_o_pos_one[1];
        assign w_o_one_position[0] = LOPD16_o_zero_flag ? LOPD8_o_pos_one[0] : LOPD16_o_pos_one[0];
        assign o_one_position = o_zero_flag ? '0 : w_o_one_position;
        endmodule

Verision1/03_verif/SubModule/LOPD_UNIT/LOPD_24BIT/Verilator/coverage/annotated_src/tb_LOPD_24bit.sv
//      // verilator_coverage annotation
        `timescale 1ns/1ps
        
        module tb_LOPD_24bit();
        
            // ================= PARAMETERS ================= //
            parameter SIZE_DATA = 24;
            parameter SIZE_POS  = 5; // log2(24) = 5
        
            // ================= SIGNALS ================= //
 000073     logic i_clk;
 000036     logic [SIZE_DATA-1:0] i_data;
%000002     logic [SIZE_POS-1:0]  o_pos_one;
%000002     logic                 o_zero_flag;
        
%000002     logic [SIZE_POS-1:0]  w_expect_pos;
%000002     logic                 w_expect_zero;
        
%000001     int test_count = 0;
%000001     int test_pass  = 0;
        
            // ================= DUT ================= //
            LOPD_24bit #(
                .SIZE_DATA  (SIZE_DATA),
                .SIZE_LOPD  (SIZE_POS)
            ) DUT (
                .i_data         (i_data),
                .o_one_position (o_pos_one),
                .o_zero_flag    (o_zero_flag)
            );
        
            // ================= DUMP WAVE ================= //
%000000     initial begin
%000000         i_clk = 1'b0;
 000073         forever begin
 000073             #5 i_clk = ~i_clk;
                end
            end
%000001     initial begin
%000001         $dumpfile("tb_LOPD_24bit.vcd");
%000001         $dumpvars(0, tb_LOPD_24bit);
            end
        
            // ================= FUNCTION: Reference Model ================= //
 000125     function automatic void f_find_LOPD(
                input  logic [SIZE_DATA-1:0] f_i_data,
                output logic [SIZE_POS-1:0]  f_o_pos_one,
                output logic                 f_o_zero_flag
            );
                int pos;
 000125         begin
%000001             if (f_i_data == 0) begin
%000001                 f_o_pos_one   = 0;
%000001                 f_o_zero_flag = 1;
 000124             end else begin
                        // Find position of leading '1' from MSB → LSB
 000124                 for (pos = SIZE_DATA-1; pos >= 0; pos--) begin
 000357                     if (f_i_data[pos]) begin
%000000                         f_o_pos_one   = SIZE_DATA-1 - pos; // encode distance from MSB
%000000                         f_o_zero_flag = 0;
%000000                         break;
                            end
                        end
                    end
                end
            endfunction
        
            // ================= TASK: Display & Compare ================= //
 000125     task automatic Check_Result(
                input string t_name,
                input logic [SIZE_DATA-1:0] t_data,
                input logic [SIZE_POS-1:0]  exp_pos,
                input logic                 exp_zero,
                input logic [SIZE_POS-1:0]  dut_pos,
                input logic                 dut_zero
            );
                string result;
 000125         result = ((exp_pos == dut_pos) && (exp_zero == dut_zero)) ? "PASS" : "FAIL";
 000125         $display("[%s] data=%b => expect(pos=%0d, zero=%b), dut(pos=%0d, zero=%b) => %s",
 000125                  t_name, t_data, exp_pos, exp_zero, dut_pos, dut_zero, result);
 000125         test_count++;
 000125         if (result == "PASS") test_pass++;
            endtask
        
            // ================= TEST SEQUENCE ================= //
            int bit_pos;
%000001     initial begin
%000001         $display("\n=== START 8-bit LEADING ONE POSITION DETECTOR TEST ===\n");
                
%000001         @(posedge i_clk);
%000001         #1;
%000001         i_data = 24'h0;
%000001         f_find_LOPD(i_data, w_expect_pos, w_expect_zero);
%000001         Check_Result("Zero", i_data, w_expect_pos, w_expect_zero, o_pos_one, o_zero_flag);
        
                // --- Deterministic test patterns (0 → 255) ---
%000001         bit_pos = 1;
%000001         repeat (24) begin
 000024             @(posedge i_clk);
 000024             #1;
 000024             i_data  = bit_pos;
 000024             @(negedge i_clk);
 000024             f_find_LOPD(i_data, w_expect_pos, w_expect_zero);
 000024             #1;
 000024             Check_Result("Direcly", i_data, w_expect_pos, w_expect_zero, o_pos_one, o_zero_flag);
 000024             bit_pos = bit_pos << 1'b1;
                end
        
                // --- Random test cases ---
%000001         repeat (100) begin
 000100             i_data = $urandom_range(0, 16777215);
 000100             #1;
 000100             f_find_LOPD(i_data, w_expect_pos, w_expect_zero);
 000100             Check_Result("Random", i_data, w_expect_pos, w_expect_zero, o_pos_one, o_zero_flag);
                end
        
                // --- Summary ---
%000001         #5;
%000001         $display("\n==================================");
%000001         $display("========== TEST SUMMARY ==========");
%000001         $display("Total test cases: %6d", test_count);
%000001         $display("Passed          : %6d", test_pass);
%000001         $display("Failed          : %6d", test_count - test_pass);
%000001         $display("Pass rate       : %0.2f%%", (test_pass * 100.0) / test_count);
%000001         $display("==================================\n");
        
%000001         #10;
%000001         $finish;
            end
        
        endmodule

Verision1/03_verif/SubModule/LOPD_UNIT/LOPD_24BIT/tb_LOPD_24bit.vcd
$date
	Mon Nov  3 22:38:31 2025
$end
$version
	Questa Intel Starter FPGA Edition Version 2024.3
$end
$timescale
	1ps
$end

$scope module tb_LOPD_24bit $end
$var parameter 32 ! SIZE_DATA $end
$var parameter 32 " SIZE_POS $end
$var reg 1 # i_clk $end
$var reg 24 $ i_data [23:0] $end
$var reg 5 % o_pos_one [4:0] $end
$var reg 1 & o_zero_flag $end
$var reg 5 ' w_expect_pos [4:0] $end
$var reg 1 ( w_expect_zero $end
$var integer 32 ) test_count $end
$var integer 32 * test_pass $end
$var integer 32 + bit_pos $end

$scope function f_find_LOPD $end
$upscope $end

$scope task Check_Result $end
$upscope $end

$scope module DUT $end
$var parameter 32 , SIZE_DATA $end
$var parameter 32 - SIZE_LOPD $end
$var wire 1 . i_data [23] $end
$var wire 1 / i_data [22] $end
$var wire 1 0 i_data [21] $end
$var wire 1 1 i_data [20] $end
$var wire 1 2 i_data [19] $end
$var wire 1 3 i_data [18] $end
$var wire 1 4 i_data [17] $end
$var wire 1 5 i_data [16] $end
$var wire 1 6 i_data [15] $end
$var wire 1 7 i_data [14] $end
$var wire 1 8 i_data [13] $end
$var wire 1 9 i_data [12] $end
$var wire 1 : i_data [11] $end
$var wire 1 ; i_data [10] $end
$var wire 1 < i_data [9] $end
$var wire 1 = i_data [8] $end
$var wire 1 > i_data [7] $end
$var wire 1 ? i_data [6] $end
$var wire 1 @ i_data [5] $end
$var wire 1 A i_data [4] $end
$var wire 1 B i_data [3] $end
$var wire 1 C i_data [2] $end
$var wire 1 D i_data [1] $end
$var wire 1 E i_data [0] $end
$var reg 5 F o_one_position [4:0] $end
$var reg 1 G o_zero_flag $end
$var reg 16 H LOPD16_i_data [15:0] $end
$var reg 4 I LOPD16_o_pos_one [3:0] $end
$var reg 1 J LOPD16_o_zero_flag $end
$var reg 8 K LOPD8_i_data [7:0] $end
$var reg 3 L LOPD8_o_pos_one [2:0] $end
$var reg 1 M LOPD8_o_zero_flag $end
$var reg 5 N w_o_one_position [4:0] $end

$scope module LOPD_16bit_UNIT_MSB $end
$var wire 1 O i_data [15] $end
$var wire 1 P i_data [14] $end
$var wire 1 Q i_data [13] $end
$var wire 1 R i_data [12] $end
$var wire 1 S i_data [11] $end
$var wire 1 T i_data [10] $end
$var wire 1 U i_data [9] $end
$var wire 1 V i_data [8] $end
$var wire 1 W i_data [7] $end
$var wire 1 X i_data [6] $end
$var wire 1 Y i_data [5] $end
$var wire 1 Z i_data [4] $end
$var wire 1 [ i_data [3] $end
$var wire 1 \ i_data [2] $end
$var wire 1 ] i_data [1] $end
$var wire 1 ^ i_data [0] $end
$var reg 4 _ o_pos_one [3:0] $end
$var reg 1 ` o_zero_flag $end
$var reg 3 a w_pos_one_0 [2:0] $end
$var reg 1 b w_zero_flag_0 $end
$var reg 3 c w_pos_one_1 [2:0] $end
$var reg 1 d w_zero_flag_1 $end
$var reg 4 e w_o_pos_one [3:0] $end

$scope module LOPD_8bit_unit_0 $end
$var wire 1 W i_data [7] $end
$var wire 1 X i_data [6] $end
$var wire 1 Y i_data [5] $end
$var wire 1 Z i_data [4] $end
$var wire 1 [ i_data [3] $end
$var wire 1 \ i_data [2] $end
$var wire 1 ] i_data [1] $end
$var wire 1 ^ i_data [0] $end
$var reg 3 f o_pos_one [2:0] $end
$var reg 1 g o_zero_flag $end
$var reg 1 h w_zero_flag_0 $end
$var reg 2 i w_pos_one_0 [1:0] $end
$var reg 1 j w_zero_flag_1 $end
$var reg 2 k w_pos_one_1 [1:0] $end
$var reg 3 l w_o_pos_one [2:0] $end

$scope module LOPD_4bit_unit_0 $end
$var wire 1 [ i_data [3] $end
$var wire 1 \ i_data [2] $end
$var wire 1 ] i_data [1] $end
$var wire 1 ^ i_data [0] $end
$var reg 2 m o_pos_one [1:0] $end
$var reg 1 n o_zero_flag $end
$upscope $end

$scope module LOPD_4bit_unit_1 $end
$var wire 1 W i_data [3] $end
$var wire 1 X i_data [2] $end
$var wire 1 Y i_data [1] $end
$var wire 1 Z i_data [0] $end
$var reg 2 o o_pos_one [1:0] $end
$var reg 1 p o_zero_flag $end
$upscope $end
$upscope $end

$scope module LOPD_8bit_unit_1 $end
$var wire 1 O i_data [7] $end
$var wire 1 P i_data [6] $end
$var wire 1 Q i_data [5] $end
$var wire 1 R i_data [4] $end
$var wire 1 S i_data [3] $end
$var wire 1 T i_data [2] $end
$var wire 1 U i_data [1] $end
$var wire 1 V i_data [0] $end
$var reg 3 q o_pos_one [2:0] $end
$var reg 1 r o_zero_flag $end
$var reg 1 s w_zero_flag_0 $end
$var reg 2 t w_pos_one_0 [1:0] $end
$var reg 1 u w_zero_flag_1 $end
$var reg 2 v w_pos_one_1 [1:0] $end
$var reg 3 w w_o_pos_one [2:0] $end

$scope module LOPD_4bit_unit_0 $end
$var wire 1 S i_data [3] $end
$var wire 1 T i_data [2] $end
$var wire 1 U i_data [1] $end
$var wire 1 V i_data [0] $end
$var reg 2 x o_pos_one [1:0] $end
$var reg 1 y o_zero_flag $end
$upscope $end

$scope module LOPD_4bit_unit_1 $end
$var wire 1 O i_data [3] $end
$var wire 1 P i_data [2] $end
$var wire 1 Q i_data [1] $end
$var wire 1 R i_data [0] $end
$var reg 2 z o_pos_one [1:0] $end
$var reg 1 { o_zero_flag $end
$upscope $end
$upscope $end
$upscope $end

$scope module LOPD_8bit_UNIT_LSB $end
$var wire 1 | i_data [7] $end
$var wire 1 } i_data [6] $end
$var wire 1 ~ i_data [5] $end
$var wire 1 !! i_data [4] $end
$var wire 1 "! i_data [3] $end
$var wire 1 #! i_data [2] $end
$var wire 1 $! i_data [1] $end
$var wire 1 %! i_data [0] $end
$var reg 3 &! o_pos_one [2:0] $end
$var reg 1 '! o_zero_flag $end
$var reg 1 (! w_zero_flag_0 $end
$var reg 2 )! w_pos_one_0 [1:0] $end
$var reg 1 *! w_zero_flag_1 $end
$var reg 2 +! w_pos_one_1 [1:0] $end
$var reg 3 ,! w_o_pos_one [2:0] $end

$scope module LOPD_4bit_unit_0 $end
$var wire 1 "! i_data [3] $end
$var wire 1 #! i_data [2] $end
$var wire 1 $! i_data [1] $end
$var wire 1 %! i_data [0] $end
$var reg 2 -! o_pos_one [1:0] $end
$var reg 1 .! o_zero_flag $end
$upscope $end

$scope module LOPD_4bit_unit_1 $end
$var wire 1 | i_data [3] $end
$var wire 1 } i_data [2] $end
$var wire 1 ~ i_data [1] $end
$var wire 1 !! i_data [0] $end
$var reg 2 /! o_pos_one [1:0] $end
$var reg 1 0! o_zero_flag $end
$upscope $end
$upscope $end
$upscope $end
$upscope $end
$enddefinitions $end
#0
$dumpvars
0#
bx $
bx %
x&
bx '
x(
bx F
xG
bx H
bx I
xJ
bx _
x`
bx a
xb
bx f
xg
xh
bx i
bx m
xn
xj
bx k
bx o
xp
bx l
bx c
xd
bx q
xr
xs
bx t
bx x
xy
xu
bx v
bx z
x{
bx w
bx e
bx K
bx L
xM
bx &!
x'!
x(!
bx )!
bx -!
x.!
x*!
bx +!
bx /!
x0!
bx ,!
bx N
b11000 !
b101 "
b11000 ,
b101 -
b0 )
b0 *
b0 +
xE
xD
xC
xB
xA
x@
x?
x>
x=
x<
x;
x:
x9
x8
x7
x6
x5
x4
x3
x2
x1
x0
x/
x.
x%!
x$!
x#!
x"!
x!!
x~
x}
x|
x^
x]
x\
x[
xZ
xY
xX
xW
xV
xU
xT
xS
xR
xQ
xP
xO
$end
#5000
1#
#6000
b0 $
b0 '
1(
b1 )
b1 +
0E
0D
0C
0B
0A
0@
0?
0>
0=
0<
0;
0:
09
08
07
06
05
04
03
02
01
00
0/
0.
b0 H
b0 K
0%!
0$!
0#!
0"!
0!!
0~
0}
0|
0^
0]
0\
0[
0Z
0Y
0X
0W
0V
0U
0T
0S
0R
0Q
0P
0O
1{
bx0 z
b0 z
1y
bx0 x
b0 x
1p
bx0 o
b0 o
1n
bx0 m
b0 m
10!
bx0 /!
b0 /!
1.!
bx0 -!
b0 -!
b0 )!
1(!
b0 +!
1*!
b0 i
1h
b0 k
1j
b0 t
1s
b0 v
1u
1r
b1xx w
b10x w
b100 w
1g
b1xx l
b10x l
b100 l
1'!
b1xx ,!
b10x ,!
b100 ,!
1M
b0 &!
1b
b0 f
1d
b0 q
b0 c
1`
b1xxx e
b0 a
b0 L
b10xx e
b100x e
b1000 e
1J
b0 _
b0 I
bx0 N
bx00 N
bx000 N
bx0000 N
1G
b10000 N
1&
b0 F
b0 %
#10000
0#
#15000
1#
#16000
b1 $
1E
b1 K
1%!
0.!
b10 -!
b11 -!
b11 )!
0(!
0'!
b110 ,!
b111 ,!
0M
b111 &!
b111 L
0G
0&
b10000 F
b10100 N
b10110 N
b10111 N
b10111 F
b10111 %
#20000
0#
b10111 '
0(
#21000
b10 )
b1 *
b10 +
#25000
1#
#26000
b10 $
0E
1D
b10 K
0%!
1$!
b10 -!
b10 )!
b110 ,!
b110 &!
b110 L
b10110 N
b10110 F
b10110 %
#30000
0#
b10110 '
#31000
b11 )
b10 *
b100 +
#35000
1#
#36000
b100 $
0D
1C
b100 K
0$!
1#!
b11 -!
b1 -!
b1 )!
b100 ,!
b101 ,!
b101 &!
b101 L
b10100 N
b10101 N
b10101 F
b10101 %
#40000
0#
b10101 '
#41000
b100 )
b11 *
b1000 +
#45000
1#
#46000
b1000 $
0C
1B
b1000 K
0#!
1"!
b0 -!
b0 )!
b100 ,!
b100 &!
b100 L
b10100 N
b10100 F
b10100 %
#50000
0#
b10100 '
#51000
b101 )
b100 *
b10000 +
#55000
1#
#56000
b10000 $
0B
1A
b10000 K
0"!
1!!
00!
b10 /!
b11 /!
1.!
1(!
b11 +!
0*!
b101 ,!
b111 ,!
b11 ,!
b11 &!
b11 L
b10000 N
b10010 N
b10011 N
b10011 F
b10011 %
#60000
0#
b10011 '
#61000
b110 )
b101 *
b100000 +
#65000
1#
#66000
b100000 $
0A
1@
b100000 K
0!!
1~
b10 /!
b10 +!
b10 ,!
b10 &!
b10 L
b10010 N
b10010 F
b10010 %
#70000
0#
b10010 '
#71000
b111 )
b110 *
b1000000 +
#75000
1#
#76000
b1000000 $
0@
1?
b1000000 K
0~
1}
b11 /!
b1 /!
b1 +!
b0 ,!
b1 ,!
b1 &!
b1 L
b10000 N
b10001 N
b10001 F
b10001 %
#80000
0#
b10001 '
#81000
b1000 )
b111 *
b10000000 +
#85000
1#
#86000
b10000000 $
0?
1>
b10000000 K
0}
1|
b0 /!
b0 +!
b0 ,!
b0 &!
b0 L
b10000 N
b10000 F
b10000 %
#90000
0#
b10000 '
#91000
b1001 )
b1000 *
b100000000 +
#95000
1#
#96000
b100000000 $
0>
1=
b1 H
b0 K
0|
1^
0n
b10 m
b11 m
10!
1*!
b11 i
0h
0g
b110 l
b111 l
1'!
b100 ,!
1M
0b
b111 f
b111 a
0`
1G
1&
b0 F
0J
b1000 _
b1100 e
b1110 e
b1111 e
b1111 _
b1111 I
0G
b0 N
b0 %
0&
b1000 N
b1100 N
b1110 N
b1111 N
b1111 F
b1111 %
#100000
0#
b1111 '
#101000
b1010 )
b1001 *
b1000000000 +
#105000
1#
#106000
b1000000000 $
0=
1<
b10 H
0^
1]
b10 m
b10 i
b110 l
b110 f
b110 a
b1110 e
b1110 _
b1110 I
b1110 N
b1110 F
b1110 %
#110000
0#
b1110 '
#111000
b1011 )
b1010 *
b10000000000 +
#115000
1#
#116000
b10000000000 $
0<
1;
b100 H
0]
1\
b11 m
b1 m
b1 i
b100 l
b101 l
b101 f
b101 a
b1100 e
b1101 e
b1101 _
b1101 I
b1100 N
b1101 N
b1101 F
b1101 %
#120000
0#
b1101 '
#121000
b1100 )
b1011 *
b100000000000 +
#125000
1#
#126000
b100000000000 $
0;
1:
b1000 H
0\
1[
b0 m
b0 i
b100 l
b100 f
b100 a
b1100 e
b1100 _
b1100 I
b1100 N
b1100 F
b1100 %
#130000
0#
b1100 '
#131000
b1101 )
b1100 *
b1000000000000 +
#135000
1#
#136000
b1000000000000 $
0:
19
b10000 H
0[
1Z
0p
b10 o
b11 o
1n
1h
b11 k
0j
b101 l
b111 l
b11 l
b11 f
b11 a
b1000 e
b1010 e
b1011 e
b1011 _
b1011 I
b1000 N
b1010 N
b1011 N
b1011 F
b1011 %
#140000
0#
b1011 '
#141000
b1110 )
b1101 *
b10000000000000 +
#145000
1#
#146000
b10000000000000 $
09
18
b100000 H
0Z
1Y
b10 o
b10 k
b10 l
b10 f
b10 a
b1010 e
b1010 _
b1010 I
b1010 N
b1010 F
b1010 %
#150000
0#
b1010 '
#151000
b1111 )
b1110 *
b100000000000000 +
#155000
1#
#156000
b100000000000000 $
08
17
b1000000 H
0Y
1X
b11 o
b1 o
b1 k
b0 l
b1 l
b1 f
b1 a
b1000 e
b1001 e
b1001 _
b1001 I
b1000 N
b1001 N
b1001 F
b1001 %
#160000
0#
b1001 '
#161000
b10000 )
b1111 *
b1000000000000000 +
#165000
1#
#166000
b1000000000000000 $
07
16
b10000000 H
0X
1W
b0 o
b0 k
b0 l
b0 f
b0 a
b1000 e
b1000 _
b1000 I
b1000 N
b1000 F
b1000 %
#170000
0#
b1000 '
#171000
b10001 )
b10000 *
b10000000000000000 +
#175000
1#
#176000
b10000000000000000 $
06
15
b100000000 H
0W
1V
0y
b10 x
b11 x
1p
1j
b11 t
0s
0r
b110 w
b111 w
1g
b100 l
1b
0d
b111 q
b111 c
b0 e
b0 _
b100 e
b110 e
b111 e
b111 _
b111 I
b0 N
b100 N
b110 N
b111 N
b111 F
b111 %
#180000
0#
b111 '
#181000
b10010 )
b10001 *
b100000000000000000 +
#185000
1#
#186000
b100000000000000000 $
05
14
b1000000000 H
0V
1U
b10 x
b10 t
b110 w
b110 q
b110 c
b110 e
b110 _
b110 I
b110 N
b110 F
b110 %
#190000
0#
b110 '
#191000
b10011 )
b10010 *
b1000000000000000000 +
#195000
1#
#196000
b1000000000000000000 $
04
13
b10000000000 H
0U
1T
b11 x
b1 x
b1 t
b100 w
b101 w
b101 q
b101 c
b100 e
b101 e
b101 _
b101 I
b100 N
b101 N
b101 F
b101 %
#200000
0#
b101 '
#201000
b10100 )
b10011 *
b10000000000000000000 +
#205000
1#
#206000
b10000000000000000000 $
03
12
b100000000000 H
0T
1S
b0 x
b0 t
b100 w
b100 q
b100 c
b100 e
b100 _
b100 I
b100 N
b100 F
b100 %
#210000
0#
b100 '
#211000
b10101 )
b10100 *
b100000000000000000000 +
#215000
1#
#216000
b100000000000000000000 $
02
11
b1000000000000 H
0S
1R
0{
b10 z
b11 z
1y
1s
b11 v
0u
b101 w
b111 w
b11 w
b11 q
b11 c
b0 e
b10 e
b11 e
b11 _
b11 I
b0 N
b10 N
b11 N
b11 F
b11 %
#220000
0#
b11 '
#221000
b10110 )
b10101 *
b1000000000000000000000 +
#225000
1#
#226000
b1000000000000000000000 $
01
10
b10000000000000 H
0R
1Q
b10 z
b10 v
b10 w
b10 q
b10 c
b10 e
b10 _
b10 I
b10 N
b10 F
b10 %
#230000
0#
b10 '
#231000
b10111 )
b10110 *
b10000000000000000000000 +
#235000
1#
#236000
b10000000000000000000000 $
00
1/
b100000000000000 H
0Q
1P
b11 z
b1 z
b1 v
b0 w
b1 w
b1 q
b1 c
b0 e
b1 e
b1 _
b1 I
b0 N
b1 N
b1 F
b1 %
#240000
0#
b1 '
#241000
b11000 )
b10111 *
b100000000000000000000000 +
#245000
1#
#246000
b100000000000000000000000 $
0/
1.
b1000000000000000 H
0P
1O
b0 z
b0 v
b0 w
b0 q
b0 c
b0 e
b0 _
b0 I
b0 N
b0 F
b0 %
#250000
0#
b0 '
#251000
b11001 )
b11000 *
b1000000000000000000000000 +
b1100110111110110100100 $
1C
1@
1>
1=
1;
1:
19
18
17
15
14
11
10
0.
b11001101111101 H
b10100100 K
1#!
1~
1|
1^
1\
1[
1Z
1Y
1X
1V
1U
1R
1Q
0O
b10 z
0y
b10 x
0p
b1 o
0n
00!
0.!
b1 -!
b1 )!
0(!
0*!
0h
b1 k
0j
b10 t
0s
b10 v
b10 w
b101 l
b1 l
0g
b0 ,!
0'!
0M
0b
b1 f
b10 q
b10 c
b1 a
b10 e
b10 _
b10 I
b10 N
b10 F
b10 %
#252000
b10 '
b11010 )
b11001 *
b100001001100011111000110 $
1D
0@
1?
1<
0:
09
08
16
05
04
13
01
00
1.
b1000010011000111 H
b11000110 K
1$!
0~
1}
1]
0[
0Z
0Y
1W
0V
0U
1T
0R
0Q
1O
b0 z
b11 x
b1 x
b0 o
b1 m
b1 i
b0 k
b1 t
b0 v
b0 w
b0 l
b0 f
b0 q
b0 c
b0 a
b0 e
b0 _
b0 I
b0 N
b0 F
b0 %
#253000
b0 '
b11011 )
b11010 *
b11110110100110011110 $
1B
1A
0?
0<
0;
1:
18
06
15
14
12
0.
b111101101001 H
b10011110 K
1"!
1!!
0}
0]
0\
1[
1Y
0W
1V
1U
1S
0O
1{
b0 x
b1 o
b0 m
b0 -!
b0 )!
b0 i
b1 k
b0 t
1u
b100 w
b1 l
b1 f
b100 q
b100 c
b1 a
b100 e
b100 _
b100 I
b100 N
b100 F
b100 %
#254000
b100 '
b11100 )
b11011 *
b110111101001111010111110 $
1@
0=
1<
1;
19
08
07
16
05
11
1/
1.
b1101111010011110 H
b10111110 K
1~
0^
1]
1\
1Z
0Y
0X
1W
0V
1R
1P
1O
0{
b0 o
b0 k
0u
b0 w
b0 l
b0 f
b0 q
b0 c
b0 a
b0 e
b0 _
b0 I
b0 N
b0 F
b0 %
#255000
1#
b0 '
b11101 )
b11100 *
b11000011100100000010001 $
1E
0D
0C
0B
0@
0>
0<
0;
09
17
15
04
03
02
01
10
0.
b110000111001000 H
b10001 K
1%!
0$!
0#!
0"!
0~
0|
0]
0\
0Z
1X
1V
0U
0T
0S
0R
1Q
0O
b1 z
b10 x
b11 x
b10 /!
b11 /!
b10 -!
b11 -!
b11 )!
b11 +!
b11 t
b1 v
b1 w
b10 ,!
b11 ,!
b11 &!
b1 q
b1 c
b11 L
b1 e
b1 _
b1 I
b1 N
b1 F
b1 %
#256000
b1 '
b11110 )
b11101 *
b100011111101011101000101 $
1C
0A
1?
1=
1<
1;
0:
19
14
13
12
00
0/
1.
b1000111111010111 H
b1000101 K
1#!
0!!
1}
1^
1]
1\
0[
1Z
1U
1T
1S
0Q
0P
1O
b0 z
b1 x
b0 x
b1 m
b1 /!
b1 -!
b1 )!
b1 +!
b1 i
b0 t
b0 v
b0 w
b1 ,!
b1 &!
b0 q
b0 c
b1 L
b0 e
b0 _
b0 I
b0 N
b0 F
b0 %
#257000
b0 '
b11111 )
b11110 *
b110011011110010110110001 $
0C
1A
1@
0?
1>
0<
09
18
04
1/
b1100110111100101 H
b10110001 K
0#!
1!!
1~
0}
1|
0]
0Z
1Y
0U
1P
b0 /!
b11 -!
b11 )!
b0 +!
b0 ,!
b0 &!
b0 L
