03_verfi/SubModule/SUM_unit/coverage/annotated_src/CLA_4bit.sv
//      // verilator_coverage annotation
        module CLA_4bit (
 001743     input  logic [3:0]  a,
 001733     input  logic [3:0]  b,
 001887     input  logic        cin,
 001732     output logic [3:0]  sum,
 000398     output logic        o_p,
 001785     output logic        o_g
        );
 001266     logic [3:0] w_g, w_p;
 001771     logic [3:0] w_c;
        
            assign w_g = a & b;
            assign w_p = a ^ b;
        
%000007     always_comb begin
%000007         w_c[0] = cin;
%000007         w_c[1] = w_g[0] | (w_p[0] & w_c[0]);
%000007         w_c[2] = w_g[1] | (w_p[1] & w_g[0]) | (w_p[1] & w_p[0] & w_c[0]);
%000007         w_c[3] = w_g[2] | (w_p[2] & w_g[1]) | (w_p[2] & w_p[1] & w_g[0])
%000007                            | (w_p[2] & w_p[1] & w_p[0] & w_c[0]);
            end
        
            assign sum = w_p ^ w_c;
        
            assign o_p = &w_p;
            assign o_g = w_g[3] | (w_p[3] & w_g[2])
                                | (w_p[3] & w_p[2] & w_g[1])
                                | (w_p[3] & w_p[2] & w_p[1] & w_g[0]);
        
        endmodule

Verision1/02_rlt/CLA_28bit.sv
module CLA_28bit(
    input logic         i_carry,
    input logic [27:0]  i_data_a,
    input logic [27:0]  i_data_b,
    output logic [27:0] o_sum,
    output logic        o_carry
);

logic [7:0] w_c;
logic [6:0] w_p;
logic [6:0] w_g;

genvar i;
generate
    assign w_c[0] = i_carry;

    CLA_4bit CLA_4BIT_UNIT_0 (
        .a      (i_data_a[3:0]),
        .b      (i_data_b[3:0]),
        .cin    (w_c[0]),
        .sum    (o_sum[3:0]),
        .o_p    (w_p[0]),
        .o_g    (w_g[0])
    );
    
    assign w_c[1] = w_g[0] | (w_p[0] & w_c[0]);
    for (i = 1; i < 7; i = i + 1) begin : CLA_BLOCK_GEN
        CLA_4bit CLA_4BIT_UNIT_1 (
            .a      (i_data_a[(i*4)+3 : i*4]),
            .b      (i_data_b[(i*4)+3 : i*4]),
            .cin    (w_c[i]),
            .sum    (o_sum[(i*4)+3 : i*4]),
            .o_p    (w_p[i]),
            .o_g    (w_g[i])
        );        
        assign w_c[i+1] = w_g[i] | (w_p[i] & w_c[i]);
    end
endgenerate

assign o_carry = w_c[7];

endmodule

02_rtl/ALU/SUM_unit.sv
module SUM_unit #(
    parameter SIZE_DATA = 28
)(
    input  logic                     i_carry,
    input  logic [SIZE_DATA-1:0]     i_data_a,
    input  logic [SIZE_DATA-1:0]     i_data_b,
    output logic [SIZE_DATA-1:0]     o_sum,
    output logic                     o_carry
);

CLA_28bit CLA_28BIT_UNIT (
    .i_carry    (i_carry),
    .i_data_a   (i_data_a),
    .i_data_b   (i_data_b),
    .o_sum      (o_sum),
    .o_carry    (o_carry)
);

endmodule

03_verfi/SubModule/SUM_unit/tb_SUM_unit.sv
`timescale 1ns/1ps

module tb_SUM_unit();

    // ---------------- PARAMETER ----------------
    parameter SIZE_DATA = 28;
    parameter NUM_TEST  = 500;

    // ---------------- SIGNAL ----------------
    logic                     i_carry;
    logic [SIZE_DATA-1:0]     i_data_a;
    logic [SIZE_DATA-1:0]     i_data_b;
    logic [SIZE_DATA-1:0]     o_sum;
    logic                     o_carry;

    logic [SIZE_DATA-1:0]     expected_sum;
    logic                     expected_carry;

    integer i;
    integer pass_count = 0;
    integer fail_count = 0;

    // ---------------- DUT ----------------
    SUM_unit #(
        .SIZE_DATA (SIZE_DATA)
    ) DUT (
        .i_carry (i_carry),
        .i_data_a (i_data_a),
        .i_data_b (i_data_b),
        .o_sum    (o_sum),      // nếu trong SUM_unit đầu ra là `o`, thay bằng `.o(o_sum)`
        .o_carry  (o_carry)
    );

    initial begin
        $dumpfile("tb_SUM_unit.vcd");
        $dumpvars(0, tb_SUM_unit);
    end

    // ---------------- TEST PROCESS ----------------
    initial begin
        $display("============================================");
        $display(">>> TEST SUM UNIT (%0d-bit) <<<", SIZE_DATA);
        $display("============================================");

        // Run NUM_TEST times
        for (i = 0; i < NUM_TEST; i++) begin
            // Random inputs
            i_data_a = $urandom_range(0, 2**SIZE_DATA - 1);
            i_data_b = $urandom_range(0, 2**SIZE_DATA - 1);
            i_carry  = $urandom_range(0, 1);

            #1; // wait for combinational logic to settle

            // Expected value (mô phỏng phép cộng thật)
            {expected_carry, expected_sum} = {1'b0, i_data_a} + {1'b0, i_data_b} + {{(SIZE_DATA-1){1'b0}}, i_carry};

            // Compare DUT vs expected
            if ((o_sum === expected_sum) && (o_carry === expected_carry)) begin
                pass_count++;
                $display("Test %0d: PASS | A=%h | B=%h | Cin=%b | SUM=%h | Cout=%b",
                         i, i_data_a, i_data_b, i_carry, o_sum, o_carry);
            end else begin
                fail_count++;
                $display("Test %0d: FAIL | A=%h | B=%h | Cin=%b | DUT_SUM=%h | EXP_SUM=%h | DUT_Cout=%b | EXP_Cout=%b",
                         i, i_data_a, i_data_b, i_carry,
                         o_sum, expected_sum, o_carry, expected_carry);
            end
        end

        // Summary
        $display("============================================");
        $display("Total Tests : %0d", NUM_TEST);
        $display("PASS         : %0d", pass_count);
        $display("FAIL         : %0d", fail_count);
        $display("============================================");

        if (fail_count == 0)
            $display("✅ ALL TESTS PASSED!");
        else
            $display("❌ SOME TESTS FAILED!");

        $finish;
    end

endmodule

03_verfi/SubModule/SUM_unit/tb_SUM_unit.vcd
$version Generated by VerilatedVcd $end
$timescale 1ps $end
 $scope module TOP $end
  $scope module tb_SUM_unit $end
   $var wire 32 n SIZE_DATA [31:0] $end
   $var wire 32 o NUM_TEST [31:0] $end
   $var wire 1 # i_carry $end
   $var wire 28 $ i_data_a [27:0] $end
   $var wire 28 % i_data_b [27:0] $end
   $var wire 28 k o_sum [27:0] $end
   $var wire 1 W o_carry $end
   $var wire 28 & expected_sum [27:0] $end
   $var wire 1 ' expected_carry $end
   $var wire 32 ( i [31:0] $end
   $var wire 32 ) pass_count [31:0] $end
   $var wire 32 * fail_count [31:0] $end
   $scope module DUT $end
    $var wire 32 n SIZE_DATA [31:0] $end
    $var wire 1 # i_carry $end
    $var wire 28 $ i_data_a [27:0] $end
    $var wire 28 % i_data_b [27:0] $end
    $var wire 28 k o_sum [27:0] $end
    $var wire 1 W o_carry $end
    $scope module CLA_28BIT_UNIT $end
     $var wire 1 # i_carry $end
     $var wire 28 $ i_data_a [27:0] $end
     $var wire 28 % i_data_b [27:0] $end
     $var wire 28 k o_sum [27:0] $end
     $var wire 1 W o_carry $end
     $var wire 8 X w_c [7:0] $end
     $var wire 7 9 w_p [6:0] $end
     $var wire 7 : w_g [6:0] $end
     $scope module CLA_4BIT_UNIT_0 $end
      $var wire 4 + a [3:0] $end
      $var wire 4 , b [3:0] $end
      $var wire 1 # cin $end
      $var wire 4 l sum [3:0] $end
      $var wire 1 ; o_p $end
      $var wire 1 < o_g $end
      $var wire 4 = w_g [3:0] $end
      $var wire 4 > w_p [3:0] $end
      $var wire 4 m w_c [3:0] $end
     $upscope $end
     $scope module CLA_BLOCK_GEN[1] $end
      $scope module CLA_4BIT_UNIT_1 $end
       $var wire 4 - a [3:0] $end
       $var wire 4 . b [3:0] $end
       $var wire 1 Y cin $end
       $var wire 4 Z sum [3:0] $end
       $var wire 1 ? o_p $end
       $var wire 1 @ o_g $end
       $var wire 4 A w_g [3:0] $end
       $var wire 4 B w_p [3:0] $end
       $var wire 4 [ w_c [3:0] $end
      $upscope $end
     $upscope $end
     $scope module CLA_BLOCK_GEN[2] $end
      $scope module CLA_4BIT_UNIT_1 $end
       $var wire 4 / a [3:0] $end
       $var wire 4 0 b [3:0] $end
       $var wire 1 \ cin $end
       $var wire 4 ] sum [3:0] $end
       $var wire 1 C o_p $end
       $var wire 1 D o_g $end
       $var wire 4 E w_g [3:0] $end
       $var wire 4 F w_p [3:0] $end
       $var wire 4 ^ w_c [3:0] $end
      $upscope $end
     $upscope $end
     $scope module CLA_BLOCK_GEN[3] $end
      $scope module CLA_4BIT_UNIT_1 $end
       $var wire 4 1 a [3:0] $end
       $var wire 4 2 b [3:0] $end
       $var wire 1 _ cin $end
       $var wire 4 ` sum [3:0] $end
       $var wire 1 G o_p $end
       $var wire 1 H o_g $end
       $var wire 4 I w_g [3:0] $end
       $var wire 4 J w_p [3:0] $end
       $var wire 4 a w_c [3:0] $end
      $upscope $end
     $upscope $end
     $scope module CLA_BLOCK_GEN[4] $end
      $scope module CLA_4BIT_UNIT_1 $end
       $var wire 4 3 a [3:0] $end
       $var wire 4 4 b [3:0] $end
       $var wire 1 b cin $end
       $var wire 4 c sum [3:0] $end
       $var wire 1 K o_p $end
       $var wire 1 L o_g $end
       $var wire 4 M w_g [3:0] $end
       $var wire 4 N w_p [3:0] $end
       $var wire 4 d w_c [3:0] $end
      $upscope $end
     $upscope $end
     $scope module CLA_BLOCK_GEN[5] $end
      $scope module CLA_4BIT_UNIT_1 $end
       $var wire 4 5 a [3:0] $end
       $var wire 4 6 b [3:0] $end
       $var wire 1 e cin $end
       $var wire 4 f sum [3:0] $end
       $var wire 1 O o_p $end
       $var wire 1 P o_g $end
       $var wire 4 Q w_g [3:0] $end
       $var wire 4 R w_p [3:0] $end
       $var wire 4 g w_c [3:0] $end
      $upscope $end
     $upscope $end
     $scope module CLA_BLOCK_GEN[6] $end
      $scope module CLA_4BIT_UNIT_1 $end
       $var wire 4 7 a [3:0] $end
       $var wire 4 8 b [3:0] $end
       $var wire 1 h cin $end
       $var wire 4 i sum [3:0] $end
       $var wire 1 S o_p $end
       $var wire 1 T o_g $end
       $var wire 4 U w_g [3:0] $end
       $var wire 4 V w_p [3:0] $end
       $var wire 4 j w_c [3:0] $end
      $upscope $end
     $upscope $end
    $upscope $end
   $upscope $end
  $upscope $end
 $upscope $end
$enddefinitions $end


#0
0#
b1001011101100111001111000100 $
b1011000111100101110110011100 %
b0000000000000000000000000000 &
0'
b00000000000000000000000000000000 (
b00000000000000000000000000000000 )
b00000000000000000000000000000000 *
b0100 +
b1100 ,
b1100 -
b1001 .
b0011 /
b1101 0
b0111 1
b0101 2
b0110 3
b1110 4
b0111 5
b0001 6
b1001 7
b1011 8
b0000000 9
b1010111 :
0;
1<
b0100 =
b1000 >
0?
1@
b1000 A
b0101 B
0C
1D
b0001 E
b1110 F
0G
0H
b0101 I
b0010 J
0K
1L
b0110 M
b1000 N
0O
0P
b0001 Q
b0110 R
0S
1T
b1001 U
b0010 V
1W
b10101110 X
1Y
b0110 Z
b0011 [
1\
b0001 ]
b1111 ^
1_
b1101 `
b1111 a
0b
b0100 c
b1100 d
1e
b1001 f
b1111 g
0h
b0100 i
b0110 j
b0100100101001101000101100000 k
b0000 l
b1000 m
b00000000000000000000000000011100 n
b00000000000000000000000111110100 o
#1000
b1000110000101110000011100100 $
b0010000101111000001101111000 %
b0100100101001101000101100000 &
1'
b00000000000000000000000000000001 (
b00000000000000000000000000000001 )
b1000 ,
b1110 -
b0111 .
b0000 /
b0011 0
b1110 1
b1000 2
b0010 3
b0111 4
b1100 5
b1000 7
b0010 8
b0001010 :
0<
b0000 =
b1100 >
b0110 A
b1001 B
0D
b0000 E
b0011 F
1H
b1000 I
b0110 J
0L
b0010 M
b0101 N
b0000 Q
b1101 R
0T
b0000 U
b1010 V
0W
b00010100 X
0Y
b0101 Z
b1100 [
b0100 ]
b0111 ^
0_
b0110 `
b0000 a
1b
b1010 c
b1111 d
0e
b1101 f
b0000 g
b1010 i
b0000 j
b1010110110100110010001011100 k
b1100 l
b0000 m
#2000
1#
b1010101001001001111010110110 $
b1010000101001111111111100100 %
b1010110110100110010001011100 &
0'
b00000000000000000000000000000010 (
b00000000000000000000000000000010 )
b0110 +
b0100 ,
b1011 -
b1110 .
b1110 /
b1111 0
b1001 1
b1111 2
b0100 3
b0100 4
b1010 5
b1010 7
b1010 8
b1001110 :
b0100 =
b0010 >
b1010 A
b0101 B
1D
b1110 E
b0001 F
b1001 I
b0100 M
b0000 N
b1011 R
1T
b1010 U
b0000 V
1W
b10011101 X
b1001 Z
b1110 ]
b1111 ^
1_
b1001 `
b1111 a
b1001 c
b1001 d
b1011 f
b0100 i
b0100 j
b0100101110011001111010011011 k
b1011 l
b1001 m
#3000
b1100110001000111000101010011 $
b1111100111100001011100100001 %
b0100101110011001111010011011 &
1'
b00000000000000000000000000000011 (
b00000000000000000000000000000011 )
b0011 +
b0001 ,
b0101 -
b0010 .
b0001 /
b0111 0
b0111 1
b0001 2
b1110 4
b1100 5
b1001 6
b1100 7
b1111 8
b1110000 :
b0001 =
0@
b0000 A
b0111 B
0D
b0001 E
b0110 F
0H
b0001 I
1L
b1010 N
1P
b1000 Q
b0101 R
b1100 U
b0011 V
b11100001 X
b0111 Z
b0000 [
0\
b1000 ]
b1110 ^
0_
b1000 `
b1110 a
0b
b0010 c
b1000 d
1e
b0110 f
b0011 g
1h
b1100 i
b1111 j
b1100011000101000100001110101 k
b0101 l
b0111 m
#4000
0#
b1111100011001010111111000101 $
b0010010100111111001110000010 %
b1100011000101000100001110101 &
b00000000000000000000000000000100 (
b00000000000000000000000000000100 )
b0101 +
b0010 ,
b1100 -
b1000 .
b1111 /
b0011 0
b1010 1
b1111 2
b1100 3
b0011 4
b1000 5
b0101 6
b1111 7
b0010 8
b0010000 9
b1001110 :
b0000 =
b0111 >
1@
b1000 A
b0100 B
1D
b0011 E
b1100 F
1H
b1010 I
b0101 J
1K
0L
b0000 M
b1111 N
0P
b0000 Q
b1101 R
b0010 U
b1101 V
b10111100 X
b0100 Z
1\
b0011 ]
b1111 ^
1_
b1010 `
b1111 a
1b
b0000 c
b1111 d
b1110 f
0h
b0001 i
b1100 j
b0001111000001010001101000111 k
b0111 l
b0000 m
#5000
b0011010110000001011000110101 $
b1101111110111100100100010010 %
b0001111000001010001101000111 &
b00000000000000000000000000000101 (
b00000000000000000000000000000101 )
b0011 -
b0001 .
b0110 /
b1001 0
b0001 1
b1100 2
b1000 3
b1011 4
b0101 5
b1111 6
b0011 7
b1101 8
b0000100 9
b1110000 :
0@
b0001 A
b0010 B
1C
0D
b0000 E
b1111 F
0H
b0000 I
b1101 J
0K
1L
b1000 M
b0011 N
1P
b0101 Q
b1010 R
b0001 U
b1110 V
b11100000 X
b0110 [
0\
b1111 ]
b0000 ^
0_
b1101 `
b0000 a
0b
b0011 c
b0000 d
b0101 f
b1111 g
1h
b1111 j
b0001010100111101111101000111 k
#6000
1#
b0100001100100011101111111101 $
b1100011010110100000111110100 %
b0001010100111101111101000111 &
b00000000000000000000000000000110 (
b00000000000000000000000000000110 )
b1101 +
b0100 ,
b1111 -
b1111 .
b1011 /
b0001 0
b0011 1
b0100 2
b0010 3
b0011 5
b0110 6
b0100 7
b1100 8
b0000000 9
b1000011 :
1<
b0100 =
b1001 >
1@
b1111 A
b0000 B
0C
b0001 E
b1010 F
b0111 J
0L
b0010 M
b1001 N
0P
b0010 Q
b0101 R
b0100 U
b1000 V
b10000111 X
1Y
b1111 Z
b1111 [
1\
b1101 ]
b0111 ^
b0111 `
b1101 c
b0100 d
0e
b1001 f
b1100 g
0h
b0000 i
b1000 j
b0000100111010111110111110010 k
b0010 l
b1011 m
#7000
0#
b0110011011010100110101011000 $
b1001110011110000010010110010 %
b0000100111010111110111110010 &
b00000000000000000000000000000111 (
b00000000000000000000000000000111 )
b1000 +
b0010 ,
b0101 -
b1011 .
b1101 /
b0100 0
b0100 1
b0000 2
b1101 3
b1111 4
b0110 5
b1100 6
b0110 7
b1001 8
b1000000 9
b0110110 :
0<
b0000 =
b1010 >
b0001 A
b1110 B
1D
b0100 E
b1001 F
b0100 J
1L
b1101 M
b0010 N
1P
b0100 Q
b1010 R
1S
0T
b0000 U
b1111 V
b11101100 X
0Y
b0000 Z
b1110 [
b0010 ]
b1011 ^
1_
b0101 `
b0001 a
b1100 c
b1110 d
1e
b0011 f
b1001 g
1h
b1111 j
b0000001111000101001000001010 k
b1010 l
b0000 m
#8000
b1010000110111000010100011110 $
b1101000111110100010110011110 %
b0000001111000101001000001010 &
b00000000000000000000000000001000 (
b00000000000000000000000000001000 )
b1110 +
b1110 ,
b0001 -
b1001 .
b0101 /
b0101 0
b1000 1
b0100 2
b1011 3
b0001 5
b0001 6
b1010 7
b1101 8
b0000000 9
b1010001 :
1<
b1110 =
b0000 >
0@
b1000 B
0D
b0101 E
b0000 F
b1100 J
b1011 M
b0100 N
0P
b0001 Q
b0000 R
0S
1T
b1000 U
b0111 V
b10100010 X
1Y
b1011 Z
b0011 [
0\
b1010 ]
b1010 ^
0_
b1100 `
b0000 a
b1010 c
b0011 g
0h
b0111 i
b0000 j
b0111001110101100101010111100 k
b1100 l
b1100 m
#9000
b1011001100110001110011101110 $
b1000001110110110101100010000 %
b0111001110101100101010111100 &
b00000000000000000000000000001001 (
b00000000000000000000000000001001 )
b0000 ,
b1110 -
b0001 .
b1100 /
b1011 0
b0001 1
b0110 2
b0011 3
b1011 4
b0011 5
b0011 6
b1011 7
b1000 8
b0000010 9
b1000100 :
0<
b0000 =
b1110 >
1?
b0000 A
b1111 B
1D
b1000 E
b0111 F
b0111 J
0L
b0011 M
b1000 N
b0011 Q
b0011 V
b10001000 X
0Y
b1111 Z
b0000 [
b0111 ]
b0000 ^
1_
b1000 `
b1111 a
b1110 c
b0110 d
0e
b0110 f
b0110 g
b0011 i
b0011011011101000011111111110 k
b1110 l
b0000 m
#10000
1#
b1010010100001110110101100011 $
b1001100111111010001011000000 %
b0011011011101000011111111110 &
b00000000000000000000000000001010 (
b00000000000000000000000000001010 )
b0011 +
b0110 -
b1100 .
b1101 /
b0010 0
b1110 1
b1010 2
b0000 3
b1111 4
b0101 5
b1001 6
b1010 7
b1001 8
b0010100 9
b1001010 :
b0011 >
0?
1@
b0100 A
b1010 B
1C
0D
b0000 E
b1111 F
1H
b1010 I
b0100 J
1K
b0000 M
b1111 N
b0001 Q
b1100 R
b10111101 X
b0010 Z
b1000 [
1\
b0000 ]
b1111 ^
b1001 `
b1101 a
1b
b0000 c
b1111 d
1e
b1111 f
b0011 g
b0011111100001001000000100100 k
b0100 l
b0111 m
#11000
b0001000110110000111100100010 $
b1111100100111000111100000110 %
b0011111100001001000000100100 &
b00000000000000000000000000001011 (
b00000000000000000000000000001011 )
b0010 +
b0110 ,
b0010 -
b0000 .
b1111 /
b1111 0
b0000 1
b1000 2
b1011 3
b0011 4
b0001 5
b0001 7
b1111 8
b0000000 9
b1000100 :
b0010 =
b0100 >
0@
b0000 A
b0010 B
0C
1D
b1111 E
b0000 F
0H
b0000 I
b1000 J
0K
b0011 M
b1000 N
b1000 R
b0001 U
b1110 V
b10001001 X
b0000 [
0\
b1110 ]
b1110 ^
b0001 a
0b
b1110 c
b0110 d
0e
b1010 f
b0010 g
b0000 i
b1110 j
b0000101011101001111000101001 k
b1001 l
b1101 m
#12000
b1001001011010011001001100011 $
b0100010101001100001001111000 %
b0000101011101001111000101001 &
b00000000000000000000000000001100 (
b00000000000000000000000000001100 )
b0011 +
b1000 ,
b0110 -
b0111 .
b0010 /
b0010 0
b0011 1
b1100 2
b1101 3
b0100 4
b0010 5
b0101 6
b1001 7
b0100 8
b0001000 9
b0010000 :
b0000 =
b1011 >
b0110 A
b0001 B
0D
b0010 E
1G
b1111 J
1L
b0100 M
b1001 N
b0000 Q
b0111 R
0T
b0000 U
b1101 V
0W
b00100001 X
b1101 Z
b1100 [
b0100 ]
b0100 ^
0_
b1111 `
b0000 a
b0001 c
b1000 d
1e
b1000 f
b1111 g
b1101 i
b0000 j
b1101100000011111010011011100 k
b1100 l
b0111 m
#13000
b0011010101001101101011001110 $
b0011100000111111111011110111 %
b1101100000011111010011011100 &
0'
b00000000000000000000000000001101 (
b00000000000000000000000000001101 )
b1110 +
b0111 ,
b1100 -
b1111 .
b1010 /
b1110 0
b1101 1
b1111 2
b0100 3
b0011 4
b0101 5
b1000 6
b0011 7
b0011 8
b0000000 9
b0001111 :
1<
b0110 =
b1001 >
1@
b1100 A
b0011 B
1D
b1010 E
b0100 F
0G
1H
b1101 I
b0010 J
0L
b0000 M
b0111 N
b1101 R
b0011 U
b0000 V
b00011111 X
1Y
b1100 Z
b1111 [
1\
b1001 ]
b1101 ^
1_
b1101 `
b1111 a
1b
b1000 c
b1111 d
0e
b1101 f
b0000 g
b0110 i
b0110 j
b0110110110001101100111000110 k
b0110 l
b1111 m
#14000
0#
b1100110110011011001110011110 $
b1100010000111101100001110111 %
b0110110110001101100111000110 &
b00000000000000000000000000001110 (
b00000000000000000000000000001110 )
b1001 -
b0111 .
b0011 /
b1000 0
b1011 1
b1101 2
b1001 3
b1101 5
b0100 6
b1100 7
b1100 8
b1101011 :
b0001 A
b1110 B
0D
b0000 E
b1011 F
b1001 I
b0110 J
b0001 M
b1010 N
1P
b0100 Q
b1001 R
1T
b1100 U
1W
b11010110 X
b0001 Z
b1100 ]
b0111 ^
0_
b1000 `
b1110 a
b1101 c
b0111 d
b0001 f
b1000 g
1h
b1001 i
b1001 j
b1001000111011000110000010101 k
b0101 l
b1100 m
#15000
1#
b0001101010000000110010101000 $
b0100101110001110001101001111 %
b1001000111011000110000010101 &
1'
b00000000000000000000000000001111 (
b00000000000000000000000000001111 )
b1000 +
b1111 ,
b1010 -
b0100 .
b1100 /
b0011 0
b0000 1
b1110 2
b1000 3
b1000 4
b1010 5
b1011 6
b0001 7
b0100 8
b0000100 9
b0110001 :
b1000 =
b0111 >
0@
b0000 A
1C
b1111 F
0H
b0000 I
b1110 J
1L
b1000 M
b0000 N
b1010 Q
b0001 R
0T
b0000 U
b0101 V
0W
b01100011 X
b1111 Z
b0001 [
0\
b1111 ]
b0000 ^
b1110 `
b0000 a
0b
b0000 c
b0000 d
1e
b0110 f
b0111 g
b0110 i
b0011 j
b0110011000001110111111111000 k
b1000 l
b1111 m
#16000
0#
b1001101100101000100110010100 $
b1101000010110010111011100010 %
b0110011000001110111111111000 &
0'
b00000000000000000000000000010000 (
b00000000000000000000000000010000 )
b0100 +
b0010 ,
b1001 -
b1110 .
b1001 /
b1110 0
b1000 1
b0010 2
b0010 3
b1011 4
b1011 5
b0000 6
b1001 7
b1101 8
b0000000 9
b1000110 :
0<
b0000 =
b0110 >
1@
b1000 A
b0111 B
0C
1D
b1000 E
b0111 F
b1010 J
0L
b0010 M
b1001 N
0P
b0000 Q
b1011 R
1T
b1001 U
b0100 V
1W
b10001100 X
0Y
b0111 Z
b0000 [
1\
b1000 ]
b1111 ^
1_
b1011 `
b0001 a
b1101 c
b0100 d
0e
b1011 f
b0000 g
0h
b0010 j
b0110101111011011100001110110 k
b0110 l
b0000 m
#17000
1#
b1111111111000001101100011111 $
b1101010101001011001100001001 %
b0110101111011011100001110110 &
1'
b00000000000000000000000000010001 (
b00000000000000000000000000010001 )
b1111 +
b1001 ,
b0001 -
b0000 .
b1011 /
b0011 0
b0001 1
b1011 2
b1100 3
b0100 4
b1111 5
b0101 6
b1111 7
b1110001 :
1<
b1001 =
0@
b0000 A
b0001 B
0D
b0011 E
b1000 F
b0001 I
1L
b0100 M
b1000 N
1P
b0101 Q
b1010 R
b1101 U
b0010 V
b11100011 X
1Y
b0010 Z
b0011 [
0\
b1110 ]
b0110 ^
0_
b1100 `
b0110 a
b0000 c
b1000 d
1e
b0101 f
b1111 g
1h
b1101 i
b1111 j
b1101010100001100111000101001 k
b1001 l
b1111 m
#18000
b0111101100001111011000011111 $
b0001101011011010111110000100 %
b1101010100001100111000101001 &
b00000000000000000000000000010010 (
b00000000000000000000000000010010 )
b0100 ,
b1000 .
b0110 /
b1111 0
b1111 1
b1010 2
b0000 3
b1101 4
b1011 5
b1010 6
b0111 7
b0001 8
b0101101 :
b0100 =
b1011 >
b1001 B
1D
b0110 E
b1001 F
1H
b1010 I
b0101 J
0L
b0000 M
b1101 N
b1010 Q
b0001 R
0T
b0001 U
b0110 V
0W
b01011011 X
b1010 Z
b0101 ]
b1100 ^
1_
b1010 `
b1111 a
1b
b1110 c
b0011 d
0e
b0100 g
b1001 i
b1001010111101010010110100100 k
b0100 l
#19000
0#
b1001001000011010011000110011 $
b1111011100101110101001001011 %
b1001010111101010010110100100 &
0'
b00000000000000000000000000010011 (
b00000000000000000000000000010011 )
b0011 +
b1011 ,
b0011 -
b0100 .
b1010 0
b1010 1
b1110 2
b0001 3
b0010 4
b0010 5
b0111 6
b1001 7
b1111 8
b1001100 :
0<
b0011 =
b1000 >
b0111 B
b0010 E
b1100 F
b0100 J
b0011 N
0P
b0010 Q
b0101 R
1T
b1001 U
1W
b10011000 X
0Y
b0111 Z
b0000 [
b0000 ]
b1001 `
b1101 a
b0100 c
b0111 d
b1001 f
b1100 g
0h
b1000 i
b1110 j
b1000100101001001000001111110 k
b1110 l
b0110 m
#20000
1#
b0110110010001010100011110011 $
b1110101100110010110011001001 %
b1000100101001001000001111110 &
1'
b00000000000000000000000000010100 (
b00000000000000000000000000010100 )
b1001 ,
b1111 -
b1100 .
b1000 /
b1100 0
b0010 2
b1000 3
b0011 4
b1100 5
b1011 6
b0110 7
b1110 8
b1100110 :
b0001 =
b1010 >
1@
b1100 A
b0011 B
b1000 E
b0100 F
0H
b0010 I
b1000 J
b1011 N
1P
b1000 Q
b0111 R
b0110 U
b1000 V
b11001101 X
b1011 Z
b1000 [
1\
b0101 ]
b0001 ^
b1101 `
b0101 a
0b
b1011 c
b0000 d
b0111 f
b0000 g
1h
b0101 i
b1101 j
b0101011110111101010110111101 k
b1101 l
b0111 m
#21000
b1011101110010110010111001010 $
b1100010010011101010101011101 %
b0101011110111101010110111101 &
b00000000000000000000000000010101 (
b00000000000000000000000000010101 )
b1010 +
b1101 ,
b1100 -
b0101 .
b0101 /
b0101 0
b0110 1
b1101 2
b1001 3
b1001 4
b1011 5
b0100 6
b1011 7
b1100 8
b0100000 9
b1011011 :
1<
b1000 =
b0111 >
b0100 A
b1001 B
0D
b0101 E
b0000 F
1H
b0100 I
b1011 J
1L
b1001 M
b0000 N
1O
0P
b0000 Q
b1111 R
b1000 U
b0111 V
b11110111 X
1Y
b0010 Z
b1011 [
b1011 ]
b1011 ^
0_
b0011 `
b1000 a
1b
b0011 c
b0011 d
1e
b0000 f
b1111 g
b1000 i
b1111 j
b1000000000110011101100101000 k
b1000 l
b1111 m
#22000
b0011111001011110110100100100 $
b0011010010011011001011101111 %
b1000000000110011101100101000 &
b00000000000000000000000000010110 (
b00000000000000000000000000010110 )
b0100 +
b1111 ,
b0010 -
b1110 .
b1101 /
b0010 0
b1110 1
b1011 2
b0101 3
b1110 5
b0011 7
b0011 8
b0000100 9
b0101011 :
b0100 =
b1011 >
b0010 A
b1100 B
1C
b0000 E
b1111 F
b1010 I
b0101 J
0L
b0001 M
b1100 N
0O
1P
b0100 Q
b1010 R
0T
b0011 U
b0000 V
0W
b01011111 X
b0001 Z
b1101 [
b0000 ]
b1111 ^
1_
b1010 `
b1111 a
b1111 c
0e
b0010 f
b1000 g
b0111 i
b0111 j
b0111001011111010000000010100 k
b0100 l
#23000
0#
b1011111010001101100101101101 $
b0110000010000011011100111001 %
b0111001011111010000000010100 &
0'
b00000000000000000000000000010111 (
b00000000000000000000000000010111 )
b1101 +
b1001 ,
b0110 -
b0011 .
b1001 /
b0111 0
b1101 1
b0011 2
b1000 3
b1000 4
b0000 6
b1011 7
b0110 8
b0000000 9
b1011101 :
b1001 =
b0100 >
0@
b0101 B
0C
1D
b0001 E
b1110 F
b0001 I
b1110 J
1L
b1000 M
b0000 N
0P
b0000 Q
b1110 R
1T
b0010 U
b1101 V
1W
b10111010 X
b1010 Z
b1111 [
0\
b1110 ^
b0001 `
b0001 c
b0001 d
1e
b1111 f
b0001 g
0h
b0001 i
b1100 j
b0001111100010001000010100110 k
b0110 l
b0010 m
#24000
b1010100001111110100011101010 $
b1101111001110011100011000010 %
b0001111100010001000010100110 &
1'
b00000000000000000000000000011000 (
b00000000000000000000000000011000 )
b1010 +
b0010 ,
b1110 -
b1100 .
b1000 /
b1000 0
b1110 1
b0111 3
b0111 4
b1000 5
b1110 6
b1010 7
b1101 8
b1101110 :
0<
b0010 =
b1000 >
1@
b1100 A
b0010 B
b1000 E
b0000 F
b0010 I
b1101 J
0L
b0111 M
1P
b1000 Q
b0110 R
b1000 U
b0111 V
b11011100 X
0Y
b1000 [
1\
b0001 ]
b0001 ^
b0010 `
b1111 c
b1111 d
0e
b0110 f
b0000 g
1h
b1000 i
b1111 j
b1000011011110010000110101100 k
b1100 l
b0100 m
#25000
1#
b0010101010100100100101010100 $
b1000101000001100101100100011 %
b1000011011110010000110101100 &
b00000000000000000000000000011001 (
b00000000000000000000000000011001 )
b0100 +
b0011 ,
b0101 -
b0010 .
b1001 /
b1011 0
b0100 1
b1100 2
b1010 3
b0000 4
b1010 5
b1010 6
b0010 7
b1000 8
b0101100 :
b0000 =
b0111 >
0@
b0000 A
b0111 B
b1001 E
b0010 F
b0100 I
b1000 J
b0000 M
b1010 N
b1010 Q
b0000 R
0T
b0000 U
b1010 V
0W
b01011001 X
b0111 Z
b0000 [
0\
b0100 ]
b0110 ^
b0001 `
b1001 a
b1011 c
b0001 d
b0100 f
b0100 g
b1011 i
b0001 j
b1011010010110001010001111000 k
b1000 l
b1111 m
