Verision1/02_rlt/LOPD_4bit.sv
module LOPD_4bit(
    input logic [3:0]       i_data  ,
    output logic [1:0]      o_pos_one,
    output logic            o_zero_flag
);

/////////////////// LDO ///////////////////
// D[3] | D[2] | D[1] | D[0] |PO[3] | PO[2] | PO[1] | PO[0] | ZERO_FLAG |
//   0  |   0  |   0  |   0  |  0   |   0   |   0   |   0   |     1     |
//   0  |   0  |   0  |   1  |  0   |   0   |   0   |   1   |     0     |
//   0  |   0  |   1  |   X  |  0   |   0   |   1   |   0   |     0     |
//   0  |   1  |   X  |   X  |  0   |   1   |   0   |   0   |     0     |
//   1  |   X  |   X  |   X  |  1   |   0   |   0   |   0   |     0     |
/////////////////// LDOD ///////////////////
// D[3] | D[2] | D[1] | D[0] | PO[1] | PO[0] | ZERO_FLAG |
//   0  |   0  |   0  |   0  |   0   |   0   |     1     |
//   0  |   0  |   0  |   1  |   0   |   0   |     0     |
//   0  |   0  |   1  |   X  |   0   |   1   |     0     |
//   0  |   1  |   X  |   X  |   1   |   0   |     0     |
//   1  |   X  |   X  |   X  |   1   |   1   |     0     |

// assign o_zero_flag = ~( (i_data[3] | i_data[2]) | (i_data[1] | i_data[0]) ) ;
assign o_zero_flag = ~( |i_data );  // Toán tử reduction OR
assign o_pos_one[1] = i_data[3] | i_data[2];
assign o_pos_one[0] = ((~(i_data[3] | i_data[2])) & (i_data[1])) |  (i_data[3]);

endmodule

Verision1/02_rlt/LOPD_8bit.sv
module LOPD_8bit(
    input logic [7:0]       i_data  ,
    output logic [2:0]      o_pos_one,
    output logic            o_zero_flag
);

////////////////////////////////////////////////////////////
// LOPD_4bit_unit_0
////////////////////////////////////////////////////////////
logic w_zero_flag_0;
logic [1:0] w_pos_one_0;
LOPD_4bit LOPD_4bit_unit_0 (
    .i_data         (i_data[3:0]),
    .o_pos_one      (w_pos_one_0),
    .o_zero_flag    (w_zero_flag_0)
);

////////////////////////////////////////////////////////////
// LOPD_4bit_unit_1
////////////////////////////////////////////////////////////
logic w_zero_flag_1;
logic [1:0] w_pos_one_1;
LOPD_4bit LOPD_4bit_unit_1 (
    .i_data         (i_data[7:4]),
    .o_pos_one      (w_pos_one_1),
    .o_zero_flag    (w_zero_flag_1)
);

////////////////////////////////////////////////////////////
// LOD_8bit_unit
////////////////////////////////////////////////////////////
assign o_zero_flag = w_zero_flag_0 & w_zero_flag_1;
assign o_pos_one[2] = ~(w_zero_flag_0);
assign o_pos_one[1] = (w_zero_flag_0) ? w_pos_one_1[1] : w_pos_one_0[1];
assign o_pos_one[0] = (w_zero_flag_0) ? w_pos_one_1[0] : w_pos_one_0[0];

endmodule

02_rtl/LOPD/LOPD_16bit.sv
module LOPD_16bit(
    input logic [16:0]       i_data  ,
    output logic [3:0]      o_pos_one,
    output logic            o_zero_flag
);


////////////////////////////////////////////////////////////
// LOPD_8bit_unit_0
////////////////////////////////////////////////////////////
logic [2:0]         w_pos_one_0;  
logic               w_zero_flag_0;
LOPD_8bit LOPD_8bit_unit_0(
    .i_data         (i_data[7:0]),
    .o_pos_one      (w_pos_one_0),
    .o_zero_flag    (w_zero_flag_0)
);
////////////////////////////////////////////////////////////
// LOPD_8bit_unit_1
////////////////////////////////////////////////////////////
logic [2:0]         w_pos_one_1;  
logic               w_zero_flag_1;
LOPD_8bit LOPD_8bit_unit_1(
    .i_data         (i_data[15:8]),
    .o_pos_one      (w_pos_one_1),
    .o_zero_flag    (w_zero_flag_1)
);

////////////////////////////////////////////////////////////
// LOD_16bit_unit
////////////////////////////////////////////////////////////
assign o_zero_flag = w_zero_flag_0 & w_zero_flag_1;
assign o_pos_one[3] = ~(w_zero_flag_1);
assign o_pos_one[2] = w_zero_flag_1 ? w_pos_one_0[2] : w_pos_one_1[2];
assign o_pos_one[1] = w_zero_flag_1 ? w_pos_one_0[1] : w_pos_one_1[1];
assign o_pos_one[0] = w_zero_flag_1 ? w_pos_one_0[0] : w_pos_one_1[0];
endmodule

02_rtl/LOPD/LOPD_32bit.sv
module LOPD_32bit (
    input logic [31:0]          i_data      ,
    output logic [4:0]          o_pos_one   ,
    output logic                o_zero_flag  
);

////////////////////////////////////////////////////////////
// LOPD_16bit_unit_0
////////////////////////////////////////////////////////////
logic [3:0]         w_pos_one_0;  
logic               w_zero_flag_0;
LOPD_16bit LOPD_16bit_unit_0(
    .i_data         (i_data[15:0]),
    .o_pos_one      (w_pos_one_0),
    .o_zero_flag    (w_zero_flag_0)
);
////////////////////////////////////////////////////////////
// LOPD_16bit_unit_1
////////////////////////////////////////////////////////////
logic [3:0]         w_pos_one_1;  
logic               w_zero_flag_1;
LOPD_16bit LOPD_16bit_unit_1(
    .i_data         (i_data[31:16]),
    .o_pos_one      (w_pos_one_1),
    .o_zero_flag    (w_zero_flag_1)
);

////////////////////////////////////////////////////////////
// LOD_16bit_unit
////////////////////////////////////////////////////////////
assign o_zero_flag = w_zero_flag_0 & w_zero_flag_1;
assign o_pos_one[4] = ~(w_zero_flag_1);
assign o_pos_one[3] = w_zero_flag_1 ? w_pos_one_1[3] : w_pos_one_0[3];
assign o_pos_one[2] = w_zero_flag_1 ? w_pos_one_1[2] : w_pos_one_0[2];
assign o_pos_one[1] = w_zero_flag_1 ? w_pos_one_1[1] : w_pos_one_0[1];
assign o_pos_one[0] = w_zero_flag_1 ? w_pos_one_1[0] : w_pos_one_0[0];

endmodule

04_impl/LOPD_unit/LOPD_unit.sv
module LOPD_unit #(
    parameter SIZE_DATA     = 32 ,
    parameter SIZE_LOP      = 5
)(
    input logic                     i_clk   ,
    input logic                     i_rst_n ,
    input logic [SIZE_DATA-1:0]     i_addr  ,
    input logic [SIZE_DATA-1:0]     i_data  ,
    output logic [SIZE_DATA-1:0]    o_addr  ,
    output logic [SIZE_LOP-1:0]     o_one_position,
    output logic                    o_zero_flag    
);

logic [SIZE_DATA-1:0] w_i_addr, w_i_data;
logic [SIZE_DATA-1:0] w_o_addr, w_o_data;
logic [SIZE_LOP-1:0] w_one_position;
logic w_zero_flag;
always_ff @( posedge i_clk or negedge i_rst_n ) begin : flipflop_proc
    if(~i_rst_n) begin
        w_i_addr        <= '0;
        w_i_data        <= '0;
        o_addr          <= '0;
        o_one_position  <= '0;
        o_zero_flag     <= '0;
    end else begin
        w_i_addr        <= i_addr;
        w_i_data        <= i_data;
        o_addr          <= w_o_addr;
        o_one_position  <= w_one_position;
        o_zero_flag     <= w_zero_flag;
    end
end

assign w_o_addr = w_i_addr;

generate
    if(SIZE_DATA == 4) begin
        LOPD_4bit DUT(
            .i_data         (w_i_data),
            .o_pos_one      (w_one_position),
            .o_zero_flag    (w_zero_flag)
        );
    end else if(SIZE_DATA == 8) begin
        LOPD_8bit DUT(
            .i_data         (w_i_data),
            .o_pos_one      (w_one_position),
            .o_zero_flag    (w_zero_flag)
        );
    end else if(SIZE_DATA == 16) begin
        LOPD_16bit DUT(
            .i_data         (w_i_data),
            .o_pos_one      (w_one_position),
            .o_zero_flag    (w_zero_flag)
        );
    end else begin
        LOPD_32bit DUT(
            .i_data         (w_i_data),
            .o_pos_one      (w_one_position),
            .o_zero_flag    (w_zero_flag)
        );
    end
endgenerate

endmodule

03_verfi/SubModule/LOPD_unit/tb_LOPD_unit.sv
`timescale 1ns/1ps

module tb_LOPD_unit();

parameter SIZE_DATA     = 32;
parameter SIZE_LOP      = $clog2(SIZE_DATA);

logic i_clk, i_rst_n;
logic [SIZE_DATA-1:0]   i_addr;
logic [SIZE_DATA-1:0]   i_data;
logic [SIZE_DATA-1:0]   o_addr;  
logic [SIZE_LOP-1:0]    o_one_position;
logic                   o_zero_flag;

LOPD_unit #(
    .SIZE_DATA  (SIZE_DATA),
    .SIZE_LOP   (SIZE_LOP)
) DUT (
    .i_clk          (i_clk),
    .i_rst_n        (i_rst_n),
    .i_addr         (i_addr),
    .i_data         (i_data),
    .o_addr         (o_addr),
    .o_one_position (o_one_position),
    .o_zero_flag    (o_zero_flag) 
);

initial begin
    i_clk = 0;
    forever begin
        #5 i_clk = ~i_clk;
    end
end

initial begin
    $dumpfile("tb_LOPD_unit.vcd");
    $dumpvars(0, tb_LOPD_unit);
end

initial begin
    i_rst_n = 0;
    i_addr = '0;
    i_data = '0;
    #100;
    // Test zero flag
    i_rst_n = 1;
    #100;
    // Test addr
    repeat (2) begin
        @(posedge i_clk);
        #1;
        i_addr = 3;
        i_data = $urandom_range(0, SIZE_DATA);
    end
    #100;
    $finish;
end
initial begin
    $monitor("i_addr = %d | i_data = %b | o_addr = %d | o_one_position = %d | o_zero_flag = %b |",
                i_addr, i_data, o_addr, o_one_position, o_zero_flag);
end

endmodule

03_verfi/SubModule/LOPD_unit/tb_LOPD_unit.vcd
$version Generated by VerilatedVcd $end
$timescale 1ps $end
 $scope module TOP $end
  $scope module tb_LOPD_unit $end
   $var wire 32 X SIZE_DATA [31:0] $end
   $var wire 32 Y SIZE_LOP [31:0] $end
   $var wire 1 6 i_clk $end
   $var wire 1 7 i_rst_n $end
   $var wire 32 8 i_addr [31:0] $end
   $var wire 32 9 i_data [31:0] $end
   $var wire 32 # o_addr [31:0] $end
   $var wire 5 $ o_one_position [4:0] $end
   $var wire 1 % o_zero_flag $end
   $scope module DUT $end
    $var wire 32 X SIZE_DATA [31:0] $end
    $var wire 32 Y SIZE_LOP [31:0] $end
    $var wire 1 6 i_clk $end
    $var wire 1 7 i_rst_n $end
    $var wire 32 8 i_addr [31:0] $end
    $var wire 32 9 i_data [31:0] $end
    $var wire 32 # o_addr [31:0] $end
    $var wire 5 $ o_one_position [4:0] $end
    $var wire 1 % o_zero_flag $end
    $var wire 32 & w_i_addr [31:0] $end
    $var wire 32 ' w_i_data [31:0] $end
    $var wire 32 & w_o_addr [31:0] $end
    $var wire 32 Z w_o_data [31:0] $end
    $var wire 5 : w_one_position [4:0] $end
    $var wire 1 ; w_zero_flag $end
    $scope module genblk1 $end
     $scope module DUT $end
      $var wire 32 ' i_data [31:0] $end
      $var wire 5 : o_pos_one [4:0] $end
      $var wire 1 ; o_zero_flag $end
      $var wire 4 < w_pos_one_0 [3:0] $end
      $var wire 1 = w_zero_flag_0 $end
      $var wire 4 > w_pos_one_1 [3:0] $end
      $var wire 1 ? w_zero_flag_1 $end
      $scope module LOPD_16bit_unit_0 $end
       $var wire 17 ( i_data [16:0] $end
       $var wire 4 < o_pos_one [3:0] $end
       $var wire 1 = o_zero_flag $end
       $var wire 3 @ w_pos_one_0 [2:0] $end
       $var wire 1 A w_zero_flag_0 $end
       $var wire 3 B w_pos_one_1 [2:0] $end
       $var wire 1 C w_zero_flag_1 $end
       $scope module LOPD_8bit_unit_0 $end
        $var wire 8 ) i_data [7:0] $end
        $var wire 3 @ o_pos_one [2:0] $end
        $var wire 1 A o_zero_flag $end
        $var wire 1 D w_zero_flag_0 $end
        $var wire 2 E w_pos_one_0 [1:0] $end
        $var wire 1 F w_zero_flag_1 $end
        $var wire 2 G w_pos_one_1 [1:0] $end
        $scope module LOPD_4bit_unit_0 $end
         $var wire 4 * i_data [3:0] $end
         $var wire 2 E o_pos_one [1:0] $end
         $var wire 1 D o_zero_flag $end
        $upscope $end
        $scope module LOPD_4bit_unit_1 $end
         $var wire 4 + i_data [3:0] $end
         $var wire 2 G o_pos_one [1:0] $end
         $var wire 1 F o_zero_flag $end
        $upscope $end
       $upscope $end
       $scope module LOPD_8bit_unit_1 $end
        $var wire 8 , i_data [7:0] $end
        $var wire 3 B o_pos_one [2:0] $end
        $var wire 1 C o_zero_flag $end
        $var wire 1 H w_zero_flag_0 $end
        $var wire 2 I w_pos_one_0 [1:0] $end
        $var wire 1 J w_zero_flag_1 $end
        $var wire 2 K w_pos_one_1 [1:0] $end
        $scope module LOPD_4bit_unit_0 $end
         $var wire 4 - i_data [3:0] $end
         $var wire 2 I o_pos_one [1:0] $end
         $var wire 1 H o_zero_flag $end
        $upscope $end
        $scope module LOPD_4bit_unit_1 $end
         $var wire 4 . i_data [3:0] $end
         $var wire 2 K o_pos_one [1:0] $end
         $var wire 1 J o_zero_flag $end
        $upscope $end
       $upscope $end
      $upscope $end
      $scope module LOPD_16bit_unit_1 $end
       $var wire 17 / i_data [16:0] $end
       $var wire 4 > o_pos_one [3:0] $end
       $var wire 1 ? o_zero_flag $end
       $var wire 3 L w_pos_one_0 [2:0] $end
       $var wire 1 M w_zero_flag_0 $end
       $var wire 3 N w_pos_one_1 [2:0] $end
       $var wire 1 O w_zero_flag_1 $end
       $scope module LOPD_8bit_unit_0 $end
        $var wire 8 0 i_data [7:0] $end
        $var wire 3 L o_pos_one [2:0] $end
        $var wire 1 M o_zero_flag $end
        $var wire 1 P w_zero_flag_0 $end
        $var wire 2 Q w_pos_one_0 [1:0] $end
        $var wire 1 R w_zero_flag_1 $end
        $var wire 2 S w_pos_one_1 [1:0] $end
        $scope module LOPD_4bit_unit_0 $end
         $var wire 4 1 i_data [3:0] $end
         $var wire 2 Q o_pos_one [1:0] $end
         $var wire 1 P o_zero_flag $end
        $upscope $end
        $scope module LOPD_4bit_unit_1 $end
         $var wire 4 2 i_data [3:0] $end
         $var wire 2 S o_pos_one [1:0] $end
         $var wire 1 R o_zero_flag $end
        $upscope $end
       $upscope $end
       $scope module LOPD_8bit_unit_1 $end
        $var wire 8 3 i_data [7:0] $end
        $var wire 3 N o_pos_one [2:0] $end
        $var wire 1 O o_zero_flag $end
        $var wire 1 T w_zero_flag_0 $end
        $var wire 2 U w_pos_one_0 [1:0] $end
        $var wire 1 V w_zero_flag_1 $end
        $var wire 2 W w_pos_one_1 [1:0] $end
        $scope module LOPD_4bit_unit_0 $end
         $var wire 4 4 i_data [3:0] $end
         $var wire 2 U o_pos_one [1:0] $end
         $var wire 1 T o_zero_flag $end
        $upscope $end
        $scope module LOPD_4bit_unit_1 $end
         $var wire 4 5 i_data [3:0] $end
         $var wire 2 W o_pos_one [1:0] $end
         $var wire 1 V o_zero_flag $end
        $upscope $end
       $upscope $end
      $upscope $end
     $upscope $end
    $upscope $end
   $upscope $end
  $upscope $end
 $upscope $end
$enddefinitions $end


#0
b00000000000000000000000000000000 #
b00000 $
0%
b00000000000000000000000000000000 &
b00000000000000000000000000000000 '
b00000000000000000 (
b00000000 )
b0000 *
b0000 +
b00000000 ,
b0000 -
b0000 .
b00000000000000000 /
b00000000 0
b0000 1
b0000 2
b00000000 3
b0000 4
b0000 5
06
07
b00000000000000000000000000000000 8
b00000000000000000000000000000000 9
b00000 :
1;
b0000 <
1=
b0000 >
1?
b000 @
1A
b000 B
1C
1D
b00 E
1F
b00 G
1H
b00 I
1J
b00 K
b000 L
1M
b000 N
1O
1P
b00 Q
1R
b00 S
1T
b00 U
1V
b00 W
b00000000000000000000000000100000 X
b00000000000000000000000000000101 Y
b00000000000000000000000000000000 Z
#5000
16
#10000
06
#15000
16
#20000
06
#25000
16
#30000
06
#35000
16
#40000
06
#45000
16
#50000
06
#55000
16
#60000
06
#65000
16
#70000
06
#75000
16
#80000
06
#85000
16
#90000
06
#95000
16
#100000
06
17
#105000
1%
16
#110000
06
#115000
16
#120000
06
#125000
16
#130000
06
#135000
16
#140000
06
#145000
16
#150000
06
#155000
16
#160000
06
#165000
16
#170000
06
#175000
16
#180000
06
#185000
16
#190000
06
#195000
16
#200000
06
#205000
16
#206000
b00000000000000000000000000000011 8
b00000000000000000000000000011101 9
#210000
06
#215000
b00000000000000000000000000000011 &
b00000000000000000000000000011101 '
b00000000000011101 (
b00011101 )
b1101 *
b0001 +
16
b00100 :
0;
b0100 <
0=
b100 @
0A
0D
b11 E
0F
#216000
b00000000000000000000000000000010 9
#220000
06
#225000
b00000000000000000000000000000011 #
b00100 $
0%
b00000000000000000000000000000010 '
b00000000000000010 (
b00000010 )
b0010 *
b0000 +
16
b00001 :
b0001 <
b001 @
b01 E
1F
#230000
06
#235000
b00001 $
16
